{
  "district": "Jodhpur",
  "tehsils": [
    {
  "tehsil": "Bhopalgarh",
  "villages": [
    { "name": "Artiya Kalan", "name_hi": "आर्टिया कलां" },
    { "name": "Artiya Khurd", "name_hi": "आर्टिया खुर्द" },
    { "name": "Asanda", "name_hi": "असांदा" },
    { "name": "Asop", "name_hi": "आसोप" },
    { "name": "Bagoriya", "name_hi": "बगोड़िया" },
    { "name": "Bandra", "name_hi": "बांद्रा" },
    { "name": "Baori", "name_hi": "बावड़ी" },
    { "name": "Bara Kalan", "name_hi": "बाड़ा कलां" },
    { "name": "Bara Khurd", "name_hi": "बाड़ा खुर्द" },
    { "name": "Barni Kalan", "name_hi": "बर्नी कलां" },
    { "name": "Barni Khurd", "name_hi": "बर्नी खुर्द" },
    { "name": "Basni Buddha", "name_hi": "बसनी बुध्दा" },
    { "name": "Basni Cholawatan", "name_hi": "बसनी चोलावटान" },
    { "name": "Basni Harisingh", "name_hi": "बसनी हरिसिंह" },
    { "name": "Basni Jasawatan", "name_hi": "बसनी जसावटान" },
    { "name": "Basni Khariya", "name_hi": "बसनी खारिया" },
    { "name": "Basni Patan", "name_hi": "बसनी पाटन" },
    { "name": "Basni Saindwa", "name_hi": "बसनी सैण्डवा" },
    { "name": "Basni Theda", "name_hi": "बसनी थेडा" },
    { "name": "Bhairu Nagar", "name_hi": "भैरु नगर" },
    { "name": "Bhanwariya Nagar", "name_hi": "भंवरिया नगर" },
    { "name": "Bhat Koriya", "name_hi": "भाट कोरिया" },
    { "name": "Bholaram Nagar", "name_hi": "भोवाराम नगर" },
    { "name": "Bhopalgarh", "name_hi": "भोपालगढ़" },
    { "name": "Bhundana", "name_hi": "भूंडाना" },
    { "name": "Birai", "name_hi": "बिराई" },
    { "name": "Birani", "name_hi": "बीरणी" },
    { "name": "Borvi Kalan", "name_hi": "बोरवी कलां" },
    { "name": "Borvi Khurd", "name_hi": "बोरवी खुर्द" },
    { "name": "Bucheti", "name_hi": "बूचेटी" },
    { "name": "Budiyo Ki Basni", "name_hi": "बूड़ियों की बसनी" },
    { "name": "Budkiya", "name_hi": "बुडकिया" },
    { "name": "Burchha", "name_hi": "बूर्च्छा" },
    { "name": "Changawara Charana", "name_hi": "चंगावड़ा चारणा" },
    { "name": "Changawara Kalan", "name_hi": "चंगावड़ा कलां" },
    { "name": "Changawara Khurd", "name_hi": "चंगावड़ा खुर्द" },
    { "name": "Chataliya", "name_hi": "चटालिया" },
    { "name": "Chaukri Kalan", "name_hi": "चौकरी कलां" },
    { "name": "Chaukri Khurd", "name_hi": "चौकरी खुर्द" },
    { "name": "Chhapla", "name_hi": "छापला" },
    { "name": "Chhindiya", "name_hi": "छिन्दिया" },
    { "name": "Dadmi", "name_hi": "डाडमी" },
    { "name": "Dayalu Nagar", "name_hi": "दयालु नगर" },
    { "name": "Devnagar", "name_hi": "देवनगर" },
    { "name": "Devnarainpur", "name_hi": "देवनारायणपुर" },
    { "name": "Dewatra", "name_hi": "देवत्रा" },
    { "name": "Dhadhesri", "name_hi": "धधेसरी" },
    { "name": "Dhanari Khurd", "name_hi": "धनाड़ी खुर्द" },
    { "name": "Dhandhora", "name_hi": "धनधोरा" },
    { "name": "Dhoru", "name_hi": "धोरू" },
    { "name": "Dodiyal", "name_hi": "डोडियाल" },
    { "name": "Dudi Nagar", "name_hi": "डूडी नगर" },
    { "name": "Gaderi", "name_hi": "गड़ेरी" },
    { "name": "Gajsinghpura", "name_hi": "गजसिंहपुरा" },
    { "name": "Gangani", "name_hi": "गंगाणी" },
    { "name": "Ganpatsingh Nagar", "name_hi": "गणपतसिंह नगर" },
    { "name": "Garasani", "name_hi": "गरासनी" },
    { "name": "Ghodawat", "name_hi": "घोड़ावत" },
    { "name": "Godawas", "name_hi": "गोदावास" },
    { "name": "Gopal Nagar", "name_hi": "गोपाल नगर" },
    { "name": "Govindpura", "name_hi": "गोविन्दपुरा" },
    { "name": "Hadman Sagar", "name_hi": "हडमान सागर" },
    { "name": "Hanuman Nagar", "name_hi": "हनुमान नगर" },
    { "name": "Hariom Nagar", "name_hi": "हरिओम नगर" },
    { "name": "Hinganiya", "name_hi": "हिंगानिया" },
    { "name": "Hingoli", "name_hi": "हिंगोली" },
    { "name": "Hiradesar", "name_hi": "हीरादेसर" },
    { "name": "Ishwar Mahadev Nagar", "name_hi": "ईश्वर महादेव नगर" },
    { "name": "Jasnagar", "name_hi": "जसनगर" },
    { "name": "Jhalamaliya", "name_hi": "झालमालिया" },
    { "name": "Jointara", "name_hi": "जोंइटारा" },
    { "name": "Kagal", "name_hi": "कागल" },
    { "name": "Kajnau Kalan", "name_hi": "काजणाऊ कलां" },
    { "name": "Kajnau Khurd", "name_hi": "काजणाऊ खुर्द" },
    { "name": "Kalawas", "name_hi": "कलावास" },
    { "name": "Kasti", "name_hi": "कास्ती" },
    { "name": "Khangata", "name_hi": "खांगटा" },
    { "name": "Khariya Khangar", "name_hi": "खारिया खांगर" },
    { "name": "Khawaspura", "name_hi": "ख्वासपुरा" },
    { "name": "Khedi Kalan", "name_hi": "खेड़ी कलां" },
    { "name": "Khedi Khurd", "name_hi": "खेड़ी खुर्द" },
    { "name": "Kherapa", "name_hi": "खेड़ापा" },
    { "name": "Kheri Charna", "name_hi": "खेड़ी चारणा" },
    { "name": "Kheri Salwa", "name_hi": "खेड़ी सालवा" },
    { "name": "Khokhariya", "name_hi": "खोखरिया" },
    { "name": "Koor", "name_hi": "कूर" },
    { "name": "Kosana", "name_hi": "कोसाणा" },
    { "name": "Kukarda", "name_hi": "कुकारड़ा" },
    { "name": "Kumbhara", "name_hi": "कुम्भारा" },
    { "name": "Kuri", "name_hi": "कुरी" },
    { "name": "Lawari", "name_hi": "लवारी" },
    { "name": "Lawera Kalan", "name_hi": "लावेरा कलां" },
    { "name": "Lawera Khurd", "name_hi": "लावेरा खुर्द" },
    { "name": "Lunawas", "name_hi": "लूणावास" },
    { "name": "Mad Puriya", "name_hi": "मदपुरिया" },
    { "name": "Mahadeo Nagar", "name_hi": "महादेव नगर" },
    { "name": "Mailana", "name_hi": "मैल्यााना" },
    { "name": "Malar", "name_hi": "मालार" },
    { "name": "Mandli Charna", "name_hi": "मंडली चारणा" },
    { "name": "Mangeriya", "name_hi": "मंगेरिया" },
    { "name": "Melawas", "name_hi": "मेलावास" },
    { "name": "Mindoli", "name_hi": "मिंदोली" },
    { "name": "Mirasiya", "name_hi": "मीरासिया" },
    { "name": "Mornawara", "name_hi": "मोरनावाड़ा" },
    { "name": "Nadsar", "name_hi": "नाड़सर" },
    { "name": "Nagalwas", "name_hi": "नागलवास" },
    { "name": "Nandiya Prabhawati", "name_hi": "नांदिया प्रभावती" },
    { "name": "Nathu Nagar", "name_hi": "नथु नगर" },
    { "name": "Nawa Nagariya", "name_hi": "नवा नगड़िया" },
    { "name": "Netra", "name_hi": "नेत्रा" },
    { "name": "Nimbariya", "name_hi": "नीम्बड़िया" },
    { "name": "Pabu Nagar", "name_hi": "पाबू नगर" },
    { "name": "Palri Ranawata", "name_hi": "पालड़ी रणावतां" },
    { "name": "Palri Siddha", "name_hi": "पालड़ी सिद्धा" },
    { "name": "Puniyon Ki Basni", "name_hi": "पूनियों की बसनी" },
    { "name": "Rajlani", "name_hi": "राजलानी" },
    { "name": "Ram Nagar", "name_hi": "राम नगर" },
    { "name": "Rampura", "name_hi": "रामपुरा" },
    { "name": "Ramrawas Kalan", "name_hi": "रामरावास कलां" },
    { "name": "Ramrawas Khurd", "name_hi": "रामरावास खुर्द" },
    { "name": "Rarod", "name_hi": "रारोड़" },
    { "name": "Ratkuriya", "name_hi": "रातकुड़िया" },
    { "name": "Roopsar", "name_hi": "रूपसार" },
    { "name": "Rudiya", "name_hi": "रूड़िया" },
    { "name": "Salwa Khurd", "name_hi": "सालवा खुर्द" },
    { "name": "Sanwat Kua Kalan", "name_hi": "सांवत कुआं कलां" },
    { "name": "Sanwat Kua Khurd", "name_hi": "सांवत कुआं खुर्द" },
    { "name": "Saran Nagar", "name_hi": "सरन नगर" },
    { "name": "Sargiya Kalan", "name_hi": "सरगिया कलां" },
    { "name": "Sargiya Khurd", "name_hi": "सरगिया खुर्द" },
    { "name": "Satheen", "name_hi": "साथीन" },
    { "name": "Sekhniyawas", "name_hi": "शेखनियावास" },
    { "name": "Seva Gaon", "name_hi": "सेवा गांव" },
    { "name": "Sevki Kalan", "name_hi": "सेवकी कलां" },
    { "name": "Sevki Khurd", "name_hi": "सेवकी खुर्द" },
    { "name": "Shekhnagar", "name_hi": "शेख नगर" },
    { "name": "Shiv Nagar", "name_hi": "शिव नगर" },
    { "name": "Shivnath Nagar", "name_hi": "शिवनाथ नगर" },
    { "name": "Shivpura", "name_hi": "शिवपुरा" },
    { "name": "Siyara", "name_hi": "सियारां" },
    { "name": "Sopra", "name_hi": "सोप्रा" },
    { "name": "Soyla", "name_hi": "सोयला" },
    { "name": "Sri Krishan Nagar", "name_hi": "श्री कृषण नगर" },
    { "name": "Sri Krishana Nagar", "name_hi": "श्री कृष्णा नगर" },
    { "name": "Sukhdeo Nagar", "name_hi": "सुखदेव नगर" },
    { "name": "Sukhlaw Nagar", "name_hi": "सुख़लाव नगर" },
    { "name": "Surpura Kalan", "name_hi": "सूरपुरा कलां" },
    { "name": "Surpura Khurd", "name_hi": "सूरपुरा खुर्द" },
    { "name": "Suwana", "name_hi": "सुवाना" },
    { "name": "Tambariya Kalan", "name_hi": "तंबरिया कलां" },
    { "name": "Tambariya Khurd", "name_hi": "तंबरिया खुर्द" },
    { "name": "Tejpura", "name_hi": "तेजपुरा" },
    { "name": "Tigra", "name_hi": "टिगरा" },
    { "name": "Todiyana", "name_hi": "टोड़ीयाना" },
    { "name": "Udeth Nagar", "name_hi": "उदेठ नगर" },
    { "name": "Ustra", "name_hi": "ऊस्त्रा" },
    { "name": "Vishnu Nagar", "name_hi": "विष्णु नगर" }
  ]
},
    {
  "tehsil": "Jodhpur",
  "villages": [
    { "name": "Akthali", "name_hi": "अक्थाली" },
    { "name": "Alakhdara", "name_hi": "अलखदरा" },
    { "name": "Anganwa", "name_hi": "आंगनवा" },
    { "name": "Asanda", "name_hi": "असांदा" },
    { "name": "Balakua", "name_hi": "बलाकुआ" },
    { "name": "Bambor Darjiyan", "name_hi": "बम्बोर दर्जियान" },
    { "name": "Bambor Purohitan", "name_hi": "बम्बोर पुरोहितान" },
    { "name": "Banar", "name_hi": "बनाड़" },
    { "name": "Barli", "name_hi": "बारली" },
    { "name": "Barli Ner", "name_hi": "बारली नेर" },
    { "name": "Basni Bedan", "name_hi": "बसनी बेदान" },
    { "name": "Basni Charna", "name_hi": "बसनी चारणा" },
    { "name": "Basni Karwar", "name_hi": "बसनी करवार" },
    { "name": "Basni Lachhan", "name_hi": "बसनी लच्छन" },
    { "name": "Basni Nikooban", "name_hi": "बसनी निकूबन" },
    { "name": "Basni Sepha", "name_hi": "बसनी सेफा" },
    { "name": "Bawarla", "name_hi": "बावरला" },
    { "name": "Beroo", "name_hi": "बेरू" },
    { "name": "Bhagtasani", "name_hi": "भगतासनी" },
    { "name": "Bhatinda", "name_hi": "भटिंडा" },
    { "name": "Bhaton Ki Dhani", "name_hi": "भाटों की ढाणी" },
    { "name": "Bhirkali", "name_hi": "भीरकली" },
    { "name": "Birami", "name_hi": "बिरामी" },
    { "name": "Birdawas", "name_hi": "बिर्डावास" },
    { "name": "Bisalpur", "name_hi": "बिसलपुर" },
    { "name": "Bora Was", "name_hi": "बोरा वास" },
    { "name": "Budh Nagar", "name_hi": "बुद्ध नगर" },
    { "name": "Chaukhan", "name_hi": "चौखान" },
    { "name": "Chawanda", "name_hi": "चावंडा" },
    { "name": "Daijar", "name_hi": "दइजर" },
    { "name": "Daikara", "name_hi": "डाइकरा" },
    { "name": "Dangiyawas", "name_hi": "डांगीयावास" },
    { "name": "Dantiwara", "name_hi": "दंतीवाड़ा" },
    { "name": "Daon Ki Dhani", "name_hi": "दांव की ढाणी" },
    { "name": "Dawcha Pyau", "name_hi": "दवचा पियाऊ" },
    { "name": "Dedipa Nada", "name_hi": "डेडीपा नाड़ा" },
    { "name": "Deoliya", "name_hi": "देवोलिया" },
    { "name": "Desooriya Kharolan", "name_hi": "देसूरिया खारोलान" },
    { "name": "Desooriya Vishnoiyan", "name_hi": "देसूरिया विष्नोइयान" },
    { "name": "Dhayalon Ki Dhani", "name_hi": "ध्यालों की ढाणी" },
    { "name": "Dheenani Ki Dhani", "name_hi": "धीनेनी की ढाणी" },
    { "name": "Doliya", "name_hi": "डोलिया" },
    { "name": "Ghantiyala", "name_hi": "घंटियाला" },
    { "name": "Gharab", "name_hi": "घरब" },
    { "name": "Golasani", "name_hi": "गोलासनी" },
    { "name": "Goliya", "name_hi": "गोलीया" },
    { "name": "Gujrawas Khurd", "name_hi": "गुजरवास खुर्द" },
    { "name": "Hem Nagar", "name_hi": "हेम नगर" },
    { "name": "Indroka", "name_hi": "इन्द्रोका" },
    { "name": "Jajiwal Bhandariya", "name_hi": "जाजिवाल भंडारिया" },
    { "name": "Jajiwal Bhatiyan", "name_hi": "जाजिवाल भाटीयान" },
    { "name": "Jajiwal Brahmana", "name_hi": "जाजिवाल ब्राह्मणा" },
    { "name": "Jajiwal Dhandhala", "name_hi": "जाजिवाल धंधाला" },
    { "name": "Jajiwal Gehlota", "name_hi": "जाजिवाल गहलोतां" },
    { "name": "Jajiwal Godara", "name_hi": "जाजिवाल गोदारा" },
    { "name": "Jajiwal Jakharan", "name_hi": "जाजिवाल जाखरण" },
    { "name": "Jajiwal Kakrala", "name_hi": "जाजिवाल काकराला" },
    { "name": "Jajiwal Kalan", "name_hi": "जाजिवाल कलां" },
    { "name": "Jajiwal Khichiyan", "name_hi": "जाजिवाल खीचियां" },
    { "name": "Jajiwal Kutri", "name_hi": "जाजिवाल कूटड़ी" },
    { "name": "Jajiwal Sribalaji", "name_hi": "जाजिवाल श्रीबालाजी" },
    { "name": "Jajiwal Vishnoiyan", "name_hi": "जाजिवाल विश्नोइयान" },
    { "name": "Jakharo Ki Dhani", "name_hi": "जाखरो की ढाणी" },
    { "name": "Jaleli Champawatan", "name_hi": "जलेली चम्पावतान" },
    { "name": "Jaleli Daikara", "name_hi": "जलेली डाइकरा" },
    { "name": "Jaleli Faujdaran", "name_hi": "जलेली फौजदारान" },
    { "name": "Jasnath Nagar", "name_hi": "जसनाथ नगर" },
    { "name": "Jatiyawas", "name_hi": "जाटीयावास" },
    { "name": "Jhalamand", "name_hi": "झलामंड" },
    { "name": "Jheepasani", "name_hi": "झीपासनी" },
    { "name": "Jodhpur (M Corp. + OG)", "name_hi": "जोधपुर (नगर निगम + बाह्य क्षेत्र)" },
    { "name": "Joliyali", "name_hi": "जोलियाली" },
    { "name": "Kakelao", "name_hi": "काके लाो" },
    { "name": "Kanawas Ka Pana", "name_hi": "कनावास का पाना" },
    { "name": "Karani", "name_hi": "करणी" },
    { "name": "Karwari Dhani", "name_hi": "करवाड़ी ढाणी" },
    { "name": "Karwar", "name_hi": "करवार" },
    { "name": "Keroo", "name_hi": "केरू" },
    { "name": "Kharda Randheer", "name_hi": "खारदा रंधीर" },
    { "name": "Khari Kalan", "name_hi": "खारी कलां" },
    { "name": "Khari Khurd", "name_hi": "खारी खुर्द" },
    { "name": "Khatiyasani", "name_hi": "खटियासनी" },
    { "name": "Khokhari", "name_hi": "खोखरी" },
    { "name": "Khokharia", "name_hi": "खोखरिया" },
    { "name": "Kukanda", "name_hi": "कुकांडा" },
    { "name": "Kuri Bhagtasani (CT)", "name_hi": "कुरी भगतासनी (नगर)" },
    { "name": "Legon Ki Dhani", "name_hi": "लेगों की ढाणी" },
    { "name": "Lolawas", "name_hi": "लोला वास" },
    { "name": "Lordi Daijagra", "name_hi": "लोरड़ी दइजाग्रा" },
    { "name": "Lordi Doliya", "name_hi": "लोरड़ी डोलिया" },
    { "name": "Lordi-Pandit Ji", "name_hi": "लोरड़ी पंडित जी" },
    { "name": "Mahadeonagar Undera", "name_hi": "महादेवनगर उंडेरा" },
    { "name": "Manai", "name_hi": "मनई" },
    { "name": "Manaklao", "name_hi": "मनकलाो" },
    { "name": "Meglasiya", "name_hi": "मेगलासिया" },
    { "name": "Miyasani", "name_hi": "मियासनी" },
    { "name": "Mokalawas", "name_hi": "मोकरावास" },
    { "name": "Moklasani", "name_hi": "मोकलासनी" },
    { "name": "Moretuka", "name_hi": "मोरटूका" },
    { "name": "Nandara Kalan", "name_hi": "नन्दरां कलां" },
    { "name": "Nandra-Khurd", "name_hi": "नन्दरां खुर्द" },
    { "name": "Nandri (CT)", "name_hi": "नांदड़ी (नगर)" },
    { "name": "Naron Ki Dhani", "name_hi": "नारों की ढाणी" },
    { "name": "Narwa Khichiyan", "name_hi": "नरवा खीचियां" },
    { "name": "Pabupura Bhatan", "name_hi": "पाबूपुरा भाटान" },
    { "name": "Pal Village (OG)", "name_hi": "पाल गांव (बाह्य क्षेत्र)" },
    { "name": "Palasani", "name_hi": "पालासनी" },
    { "name": "Palri Khichiyan", "name_hi": "पालड़ी खीचियां" },
    { "name": "Palri Mangaliya", "name_hi": "पालड़ी मांगलिया" },
    { "name": "Palri Panwara", "name_hi": "पालड़ी पंवारां" },
    { "name": "Peethasani", "name_hi": "पीठासनी" },
    { "name": "Peethawas", "name_hi": "पीठावास" },
    { "name": "Phitkasni", "name_hi": "फिटकासनी" },
    { "name": "Pooniyon Ki Pyau", "name_hi": "पूनियों की पियाऊ" },
    { "name": "Popawas", "name_hi": "पोपा वास" },
    { "name": "Pratap Nagar", "name_hi": "प्रताप नगर" },
    { "name": "Purakhpur", "name_hi": "पुरखपुर" },
    { "name": "Rajwa", "name_hi": "राजवा" },
    { "name": "Ralawas", "name_hi": "रालावास" },
    { "name": "Ram Nagar", "name_hi": "राम नगर" },
    { "name": "Rasidan", "name_hi": "रसिदन" },
    { "name": "Rohila Kalan", "name_hi": "रोहिला कलां" },
    { "name": "Rohila Khurd", "name_hi": "रोहिला खुर्द" },
    { "name": "Roodkali", "name_hi": "रूडकली" },
    { "name": "Salori", "name_hi": "सलोरी" },
    { "name": "Salwa Kalan", "name_hi": "सालवा कलां" },
    { "name": "Sangariya (CT)", "name_hi": "सांगड़िया (नगर)" },
    { "name": "Saran Nagar", "name_hi": "सरन नगर" },
    { "name": "Sewalon Ki Dhani", "name_hi": "सेवालों की ढाणी" },
    { "name": "Shiv Sarnon Ki Dhani", "name_hi": "शिव सर्णों की ढाणी" },
    { "name": "Siriyade Gaon", "name_hi": "सिरियाड़े गांव" },
    { "name": "Sirodi", "name_hi": "सिरोड़ी" },
    { "name": "Soder Ki Dhani", "name_hi": "सोदर की ढाणी" },
    { "name": "Sooraj Basni", "name_hi": "सूरज बसनी" },
    { "name": "Surpura", "name_hi": "सुरपुरा" },
    { "name": "Thabukra", "name_hi": "थाबुकड़ा" },
    { "name": "Uchiyarda", "name_hi": "ऊंचीयारड़ा" },
    { "name": "Veer Teja Nagar", "name_hi": "वीर तेजा नगर" },
    { "name": "Vishnoiyon Ki Dhani", "name_hi": "विष्नोइयों की ढाणी" }
  ]
    },
   {
  "tehsil": "Luni",
  "villages": [
    { "name": "Ajeet Nagar", "name_hi": "अजीत नगर" },
    { "name": "Arniyala", "name_hi": "अरनियाला" },
    { "name": "Badla Nagar", "name_hi": "बदला नगर" },
    { "name": "Bajrang Nagar", "name_hi": "बजरंग नगर" },
    { "name": "Balaji Nagar", "name_hi": "बालाजी नगर" },
    { "name": "Baniyawas", "name_hi": "बनियावास" },
    { "name": "Barliya", "name_hi": "बारलिया" },
    { "name": "Basni Baghela", "name_hi": "बसनी बघेला" },
    { "name": "Basni Jhoonthan", "name_hi": "बसनी झूंठन" },
    { "name": "Basni Silawatan", "name_hi": "बसनी सिलावटान" },
    { "name": "Beota", "name_hi": "बिओटा" },
    { "name": "Bhacharna", "name_hi": "भाछरना" },
    { "name": "Bhagtasani", "name_hi": "भगतासनी" },
    { "name": "Bhakrasani", "name_hi": "भाकड़ासनी" },
    { "name": "Bhakri", "name_hi": "भाकड़ी" },
    { "name": "Bhandoo Kalan", "name_hi": "भांडू कलां" },
    { "name": "Bhandoo Khurd", "name_hi": "भांडू खुर्द" },
    { "name": "Birasani", "name_hi": "बीरासनी" },
    { "name": "Boranara", "name_hi": "बोरानाड़ा" },
    { "name": "Bujhawar", "name_hi": "बूझावर" },
    { "name": "Chainpura Bhatan", "name_hi": "चैनपुरा भाटान" },
    { "name": "Chak Barliya", "name_hi": "चक बारलिया" },
    { "name": "Chali", "name_hi": "चाली" },
    { "name": "Chawan", "name_hi": "चावन" },
    { "name": "Chawaron Ki Dhani", "name_hi": "चावरों की ढाणी" },
    { "name": "Chicharli", "name_hi": "चिचरली" },
    { "name": "Chirai Nagar", "name_hi": "चिरई नगर" },
    { "name": "Dadasar", "name_hi": "दादासर" },
    { "name": "Daipara Khichiyan", "name_hi": "दैपाड़ा खीचियां" },
    { "name": "Delumba", "name_hi": "डेलूंबा" },
    { "name": "Deopura", "name_hi": "देवपुरा" },
    { "name": "Dev Nagar", "name_hi": "देव नगर" },
    { "name": "Dhabecho Ka Gaon", "name_hi": "धाबेचो का गांव" },
    { "name": "Dhana Vishnoi", "name_hi": "धना विष्णोई" },
    { "name": "Dhandhiya", "name_hi": "धंधिया" },
    { "name": "Dhawa I", "name_hi": "धावा प्रथम" },
    { "name": "Dhawa Ii", "name_hi": "धावा द्वितीय" },
    { "name": "Dhigana", "name_hi": "धिगाणा" },
    { "name": "Dhund", "name_hi": "ढूंढ" },
    { "name": "Dhundhara", "name_hi": "ढूंढाड़ा" },
    { "name": "Dolanada", "name_hi": "डोलानाड़ा" },
    { "name": "Doli", "name_hi": "डोली" },
    { "name": "Doli Kalani", "name_hi": "डोली कलानी" },
    { "name": "Doodiya", "name_hi": "डूड़िया" },
    { "name": "Feench", "name_hi": "फींच" },
    { "name": "Gangana", "name_hi": "गंगाना" },
    { "name": "Gelawas", "name_hi": "गेळावास" },
    { "name": "Goliya Magra", "name_hi": "गोलीया मगरा" },
    { "name": "Gujrawas Kalan", "name_hi": "गुजरवास कलां" },
    { "name": "Gulab Sagar", "name_hi": "गुलाब सागर" },
    { "name": "Gura Vishnoiyan", "name_hi": "गूरा विष्नोइयान" },
    { "name": "Gurha Vishnoi Raikan", "name_hi": "गुर्हा विष्णोई रैकरण" },
    { "name": "Hamir Nagar", "name_hi": "हमीर नगर" },
    { "name": "Hanuman Nagar", "name_hi": "हनुमान नगर" },
    { "name": "Heer Khera", "name_hi": "हीरखेड़ा" },
    { "name": "Hingola", "name_hi": "हिंगोला" },
    { "name": "Imam Nagar", "name_hi": "इमाम नगर" },
    { "name": "Jambheshwar Nagar", "name_hi": "जांभेश्वर नगर" },
    { "name": "Janadesar", "name_hi": "जनादेसर" },
    { "name": "Janguwas", "name_hi": "जांगूवास" },
    { "name": "Jatiyasani", "name_hi": "जातीयासनी" },
    { "name": "Jhanwar", "name_hi": "झंवर" },
    { "name": "Jogiyasani", "name_hi": "जोगीयासनी" },
    { "name": "Kadumbanada", "name_hi": "कडूम्बनाडा" },
    { "name": "Kagnada", "name_hi": "कागनाड़ा" },
    { "name": "Kakani", "name_hi": "काकणी" },
    { "name": "Kalijal", "name_hi": "कालीजाल" },
    { "name": "Kanasar", "name_hi": "कनासर" },
    { "name": "Karni Nagar", "name_hi": "करणी नगर" },
    { "name": "Karniyali", "name_hi": "करणीयाली" },
    { "name": "Katarda", "name_hi": "कटारड़ा" },
    { "name": "Kerla", "name_hi": "केरला" },
    { "name": "Kerli", "name_hi": "केरलई" },
    { "name": "Khara Bera Bheemawata", "name_hi": "खारा बेरां भीमावटां" },
    { "name": "Khara Bera Purohitan", "name_hi": "खारा बेरां पुरोहितान" },
    { "name": "Kharda Bhandoo", "name_hi": "खारदा भांडू" },
    { "name": "Khatawas", "name_hi": "खातावास" },
    { "name": "Khejara Nara", "name_hi": "खेड़ा नारा" },
    { "name": "Khejarli Kalan", "name_hi": "खेजड़ली कलां" },
    { "name": "Khejarli Khurd", "name_hi": "खेजड़ली खुर्द" },
    { "name": "Khera Sarecha", "name_hi": "खेड़ा सरेचा" },
    { "name": "Khudala", "name_hi": "खूड़ाला" },
    { "name": "Kishanasar", "name_hi": "किशनासर" },
    { "name": "Kishanpura", "name_hi": "किशनपुरा" },
    { "name": "Krishna Khera", "name_hi": "कृष्णा खेड़ा" },
    { "name": "Krishna Nagar", "name_hi": "कृष्णा नगर" },
    { "name": "Lakhar Thumb", "name_hi": "लाखर ठूंठ" },
    { "name": "Lolasani", "name_hi": "लोला सनी" },
    { "name": "Loonawas Charna", "name_hi": "लूणावास चारणा" },
    { "name": "Loonawas Jatan", "name_hi": "लूणावास जाटान" },
    { "name": "Loonawas Kalan", "name_hi": "लूणावास कलां" },
    { "name": "Loonawas Khara", "name_hi": "लूणावास खारा" },
    { "name": "Loonawas Khurd", "name_hi": "लूणावास खुर्द" },
    { "name": "Madhopura", "name_hi": "माधोपुरा" },
    { "name": "Magrasar", "name_hi": "मागरसार" },
    { "name": "Mahadev Nagar", "name_hi": "महादेव नगर" },
    { "name": "Mangal Nagar", "name_hi": "मंगल नगर" },
    { "name": "Mehramnagar", "name_hi": "मेहरामनगर" },
    { "name": "Melawas", "name_hi": "मेलावास" },
    { "name": "Melwa", "name_hi": "मेलवा" },
    { "name": "Meran Nagar", "name_hi": "मेरन नगर" },
    { "name": "Modathali", "name_hi": "मोदाठली" },
    { "name": "Mogra Kalan", "name_hi": "मोगरा कलां" },
    { "name": "Mogra Khurd", "name_hi": "मोगरा खुर्द" },
    { "name": "Mori", "name_hi": "मोरी" },
    { "name": "Mori Joshiyan", "name_hi": "मोरी जोशियान" },
    { "name": "Mori Sothran", "name_hi": "मोरी सोथरान" },
    { "name": "Mukanpura", "name_hi": "मुखनपुरा" },
    { "name": "Nainasar", "name_hi": "नैनासर" },
    { "name": "Nandwan", "name_hi": "नांदवान" },
    { "name": "Narnadi", "name_hi": "नरनाड़ी" },
    { "name": "Naya Sajara", "name_hi": "नया सजारा" },
    { "name": "Naya Sajara Khurd", "name_hi": "नया सजारा खुर्द" },
    { "name": "Nimbala", "name_hi": "निंबला" },
    { "name": "Nimbalasar", "name_hi": "निंबालासर" },
    { "name": "Nimbli", "name_hi": "निंबली" },
    { "name": "Pabu Nara", "name_hi": "पाबू नारा" },
    { "name": "Pabupura Kumharan", "name_hi": "पाबूपुरा कुम्हारान" },
    { "name": "Pannesingh Nagar", "name_hi": "पन्नेसिंह नगर" },
    { "name": "Peeparli", "name_hi": "पीपड़ली" },
    { "name": "Peshawas", "name_hi": "पेशावास" },
    { "name": "Piprali", "name_hi": "पिपराली" },
    { "name": "Priyaron Ki Dhani", "name_hi": "प्रियारों की ढाणी" },
    { "name": "Purkhawas", "name_hi": "पुरखावास" },
    { "name": "Rabariya", "name_hi": "रबड़िया" },
    { "name": "Rabariyawas", "name_hi": "रबड़ियावास" },
    { "name": "Radnagar", "name_hi": "राडनगर" },
    { "name": "Raj Nagar", "name_hi": "राज नगर" },
    { "name": "Rajeshwar Nagar", "name_hi": "राजेश्वर नगर" },
    { "name": "Rajor", "name_hi": "राजोर" },
    { "name": "Rajpuriya", "name_hi": "राजपुरिया" },
    { "name": "Ram Nagar", "name_hi": "राम नगर" },
    { "name": "Ramgarh", "name_hi": "रामगढ़" },
    { "name": "Rana Nagar", "name_hi": "राणा नगर" },
    { "name": "Rendari", "name_hi": "रेनदड़ी" },
    { "name": "Rohichan Kalan", "name_hi": "रोहीचान कलां" },
    { "name": "Rohichan Khurd", "name_hi": "रोहीचान खुर्द" },
    { "name": "Rohila Bhandoo", "name_hi": "रोहिला भांडू" },
    { "name": "Sajara", "name_hi": "सजारा" },
    { "name": "Salawas", "name_hi": "सलावास" },
    { "name": "Salawas Rly.Station", "name_hi": "सलावास रेलवे स्टेशन" },
    { "name": "Sampat Nagar", "name_hi": "सम्पत नगर" },
    { "name": "Samrathal Nagar", "name_hi": "समरथल नगर" },
    { "name": "Sangasani", "name_hi": "सांगासनी" },
    { "name": "Sant Devaram Nagar", "name_hi": "संत देवराम नगर" },
    { "name": "Sant Likhmaram Nagar", "name_hi": "संत लिखमाराम नगर" },
    { "name": "Sar", "name_hi": "सार" },
    { "name": "Sardargarh", "name_hi": "सरदारगढ़" },
    { "name": "Sarechan", "name_hi": "सरेचन" },
    { "name": "Satlana", "name_hi": "सटलाना" },
    { "name": "Sawan Nagar", "name_hi": "सावन नगर" },
    { "name": "Senai", "name_hi": "सेनाई" },
    { "name": "Sewala", "name_hi": "सेवाला" },
    { "name": "Sewala Nagar", "name_hi": "सेवाला नगर" },
    { "name": "Shekhanada", "name_hi": "शेखनाड़ा" },
    { "name": "Sherani Nagar", "name_hi": "शेरानी नगर" },
    { "name": "Shikarpura", "name_hi": "शिकरपुरा" },
    { "name": "Shivgaon", "name_hi": "शिवगांव" },
    { "name": "Shri Rajeshwar Nagar", "name_hi": "श्री राजेश्वर नगर" },
    { "name": "Singasani", "name_hi": "सिंगासनी" },
    { "name": "Sinli", "name_hi": "सिनली" },
    { "name": "Subdand", "name_hi": "सूबडांड़" },
    { "name": "Surta Nagar", "name_hi": "सूरता नगर" },
    { "name": "Tajaliya", "name_hi": "ताजलिया" },
    { "name": "Tanawara", "name_hi": "तनावरा" },
    { "name": "Thumbali", "name_hi": "थुम्बली" },
    { "name": "Uttesar", "name_hi": "उत्तेसर" },
    { "name": "Vishawas", "name_hi": "विश्वास" },
    { "name": "Vishnu Ki Dhani", "name_hi": "विष्णु की ढाणी" }
  ]
}
,
   {
  "tehsil": "Osian",
  "villages": [
    { "name": "Jaton Ki Dhani", "name_hi": "जाटों की ढाणी" },
    { "name": "Khanu Ki Dhani", "name_hi": "खानू की ढाणी" },
    { "name": "Anwana", "name_hi": "अनवाना" },
    { "name": "Arjundeo Nagar", "name_hi": "अर्जुनदेव नगर" },
    { "name": "Asha Pura", "name_hi": "आशापुरा" },
    { "name": "Baba Ramdeonagar", "name_hi": "बाबा रामदेवनगर" },
    { "name": "Baithwasiya", "name_hi": "बैठवासिया" },
    { "name": "Bajrang Nagar", "name_hi": "बजरंग नगर" },
    { "name": "Balaji Nagar", "name_hi": "बालाजी नगर" },
    { "name": "Balarwa", "name_hi": "बलारवा" },
    { "name": "Bana Ka Bas", "name_hi": "बाना का बास" },
    { "name": "Bananiyon Ki Dhani", "name_hi": "बनानियों की ढाणी" },
    { "name": "Bapini", "name_hi": "बापिणी" },
    { "name": "Bapini Khurd", "name_hi": "बापिणी खुर्द" },
    { "name": "Bara Kotecha", "name_hi": "बड़ा कोटेचा" },
    { "name": "Bara Kotecha Khurd", "name_hi": "बड़ा कोटेचा खुर्द" },
    { "name": "Baran Kalan", "name_hi": "बारन कलां" },
    { "name": "Baran Khurd", "name_hi": "बारन खुर्द" },
    { "name": "Barawas", "name_hi": "बरावास" },
    { "name": "Bari", "name_hi": "बाड़ी" },
    { "name": "Barla Basni", "name_hi": "बरला बसनी" },
    { "name": "Barsaloo Kalan", "name_hi": "बरसलू कलां" },
    { "name": "Barsaloo Khurd", "name_hi": "बरसलू खुर्द" },
    { "name": "Barthal", "name_hi": "बारथल" },
    { "name": "Basni", "name_hi": "बसनी" },
    { "name": "Basni Bhatiyan", "name_hi": "बसनी भाटीयान" },
    { "name": "Basni Danwara", "name_hi": "बसनी दनवाड़ा" },
    { "name": "Basnitarda", "name_hi": "बसनी तर्दा" },
    { "name": "Bassi Nagar", "name_hi": "बासी नगर" },
    { "name": "Bedon Ka Bera", "name_hi": "बेडों का बेरा" },
    { "name": "Bedoo", "name_hi": "बेडू" },
    { "name": "Bedoo Kalan", "name_hi": "बेडू कलां" },
    { "name": "Beenj Wariya", "name_hi": "बींज वारिया" },
    { "name": "Begriya", "name_hi": "बेगरिया" },
    { "name": "Beh Charnan", "name_hi": "बेह चारणन" },
    { "name": "Berdon Ka Bas", "name_hi": "बेरडों का बास" },
    { "name": "Bhabhuon Ki Dhani", "name_hi": "भाभुओं की ढाणी" },
    { "name": "Bhaduon Ki Dhani", "name_hi": "भादुओं की ढाणी" },
    { "name": "Bhainser Chawandiyali", "name_hi": "भैंसर चावंडियाली" },
    { "name": "Bhainser Kootri", "name_hi": "भैंसर कूटड़ी" },
    { "name": "Bhainser Kotwali", "name_hi": "भैंसर कोटवाली" },
    { "name": "Bhairu Sagar", "name_hi": "भैरू सागर" },
    { "name": "Bhakhri", "name_hi": "भाखरी" },
    { "name": "Bhakhri Dhani", "name_hi": "भाखरी ढाणी" },
    { "name": "Bhakhron Ki Dhani", "name_hi": "भाखरों की ढाणी" },
    { "name": "Bhala Basni", "name_hi": "भला बसनी" },
    { "name": "Bhanda", "name_hi": "भांडा" },
    { "name": "Bhari Nagar", "name_hi": "भारी नगर" },
    { "name": "Bhawad", "name_hi": "भवाद" },
    { "name": "Bhawani Singh Nagar", "name_hi": "भगवानी सिंह नगर" },
    { "name": "Bheekam Kor", "name_hi": "भीकम कोर" },
    { "name": "Bheeyadiya", "name_hi": "भीयाड़िया" },
    { "name": "Bher", "name_hi": "भेर" },
    { "name": "Bhimsagar", "name_hi": "भीमसागर" },
    { "name": "Bhukero Ki Dhani", "name_hi": "भुकेरो की ढाणी" },
    { "name": "Bigmi", "name_hi": "बिग्मी" },
    { "name": "Bijariya Bavri", "name_hi": "बिजारिया बावरी" },
    { "name": "Budh Nagar", "name_hi": "बुद्ध नगर" },
    { "name": "Chain Sagar", "name_hi": "चैनसागर" },
    { "name": "Chain Sing Nagar", "name_hi": "चैन सिंह नगर" },
    { "name": "Chandaliya", "name_hi": "चंदलिया" },
    { "name": "Chandrakh", "name_hi": "चन्द्राख" },
    { "name": "Chaupasani Charnan", "name_hi": "चौपासनी चारणन" },
    { "name": "Cherai", "name_hi": "चेड़ाई" },
    { "name": "Chindri", "name_hi": "चिन्दड़ी" },
    { "name": "Dabri", "name_hi": "डाबरी" },
    { "name": "Danwara", "name_hi": "दनवाड़ा" },
    { "name": "Daukiyon Ka Bas", "name_hi": "दौकियों का बास" },
    { "name": "Daukiyon Ki Dhani", "name_hi": "दौकियों की ढाणी" },
    { "name": "Deo Nagar", "name_hi": "देव नगर" },
    { "name": "Deoraj Nagar", "name_hi": "देवराज नगर" },
    { "name": "Dhanari Kalan", "name_hi": "धनाड़ी कलां" },
    { "name": "Dharam Sagar", "name_hi": "धर्मसागर" },
    { "name": "Dholiya Nagar", "name_hi": "धोलिया नगर" },
    { "name": "Dhunariya", "name_hi": "धुनारिया" },
    { "name": "Dhundhara", "name_hi": "ढूंढाड़ा" },
    { "name": "Digari", "name_hi": "डिगाड़ी" },
    { "name": "Doli Nerwa", "name_hi": "डोली नेरवा" },
    { "name": "Ekalkhori", "name_hi": "एकलखोरी" },
    { "name": "Eramon Ki Dhani", "name_hi": "इरामों की ढाणी" },
    { "name": "Ewalo Ka Dhora", "name_hi": "इवालों का धोरा" },
    { "name": "Gagari", "name_hi": "गागड़ी" },
    { "name": "Geengala", "name_hi": "गींगाला" },
    { "name": "Ghevara", "name_hi": "घेवरा" },
    { "name": "Gopasariya", "name_hi": "गोपासरिया" },
    { "name": "Gosai Nagar", "name_hi": "गोसाई नगर" },
    { "name": "Govindpura", "name_hi": "गोविन्दपुरा" },
    { "name": "Guru Jambheswar Nagar", "name_hi": "गुरु जाम्भेश्वर नगर" },
    { "name": "Hadman Nagar", "name_hi": "हड़मान नगर" },
    { "name": "Hadman Sagar", "name_hi": "हड़मान सागर" },
    { "name": "Haniya", "name_hi": "हनिया" },
    { "name": "Hardani", "name_hi": "हरदाणी" },
    { "name": "Hari Nagar", "name_hi": "हरि नगर" },
    { "name": "Hari Om Nagar", "name_hi": "हरिओम नगर" },
    { "name": "Hariom Nagar", "name_hi": "हरिओम नगर" },
    { "name": "Haripura", "name_hi": "हरिपुरा" },
    { "name": "Harlaya", "name_hi": "हरलाया" },
    { "name": "Hastinapura", "name_hi": "हस्तिनापुर" },
    { "name": "Hatundi", "name_hi": "हटूंडी" },
    { "name": "Indon Ki Dhani", "name_hi": "इंदों की ढाणी" },
    { "name": "Indon Ki Dhani -Ii", "name_hi": "इंदों की ढाणी -II" },
    { "name": "Ishwar Nagar", "name_hi": "ईश्वर नगर" },
    { "name": "Jagdamba Nagar", "name_hi": "जगदम्बा नगर" },
    { "name": "Jaitiyawas", "name_hi": "जैटियावास" },
    { "name": "Jaiwasar", "name_hi": "जैवसार" },
    { "name": "Jakhan", "name_hi": "जाखन" },
    { "name": "Jakhro Ki Dhani", "name_hi": "जाखरो की ढाणी" },
    { "name": "Jambh Nagar", "name_hi": "जांभ नगर" },
    { "name": "Jambheswar Nagar", "name_hi": "जाम्भेश्वर नगर" },
    { "name": "Jamsagar", "name_hi": "जामसागर" },
    { "name": "Jasnath Bari", "name_hi": "जसनाथ बाड़ी" },
    { "name": "Jasnath Nagar", "name_hi": "जसनाथ नगर" },
    { "name": "Jasnathnagar", "name_hi": "जसनाथनगर" },
    { "name": "Jasnathpura", "name_hi": "जसनाथपुरा" },
    { "name": "Jatipura", "name_hi": "जाटीपुरा" },
    { "name": "Jeloo", "name_hi": "जेलू" },
    { "name": "Jeriya", "name_hi": "जेऱिया" },
    { "name": "Jhariya", "name_hi": "झारिया" },
    { "name": "Jugat Sing Nagar", "name_hi": "जुगत सिंह नगर" },
    { "name": "Jur", "name_hi": "जूर" },
    { "name": "Kandawasra Nagar", "name_hi": "कांडावासरा नगर" },
    { "name": "Kapooriya", "name_hi": "कपूरिया" },
    { "name": "Karangar Nagar", "name_hi": "करांगढ़ नगर" },
    { "name": "Karni Nagar", "name_hi": "करणी नगर" },
    { "name": "Karvasro Ki Dhani", "name_hi": "करवासरो की ढाणी" },
    { "name": "Karwan", "name_hi": "करवान" },
    { "name": "Karwaniyon Ki Dhani", "name_hi": "करवानियों की ढाणी" },
    { "name": "Kasba Nagar", "name_hi": "कस्बा नगर" },
    { "name": "Kelawa Kalan", "name_hi": "केलावा कलां" },
    { "name": "Kelawa Khurd", "name_hi": "केलावा खुर्द" },
    { "name": "Kerla Nagar", "name_hi": "केरला नगर" },
    { "name": "Kerlanada", "name_hi": "केरलानाड़ा" },
    { "name": "Khabaniya", "name_hi": "खाबानिया" },
    { "name": "Khabra Kalan", "name_hi": "खाबरा कलां" },
    { "name": "Khabra Khurd", "name_hi": "खाबरा खुर्द" },
    { "name": "Khagar Ki Dhani", "name_hi": "खगार की ढाणी" },
    { "name": "Kharda Mewasa", "name_hi": "खारड़ा म्यूसा" },
    { "name": "Khari Kalan", "name_hi": "खारी कलां" },
    { "name": "Khari Khurd", "name_hi": "खारी खुर्द" },
    { "name": "Kherla Nagar", "name_hi": "खेरला नगर" },
    { "name": "Khetasar", "name_hi": "खेड़ासर" },
    { "name": "Khindakor", "name_hi": "खिन्दाकोर" },
    { "name": "Khivsingh Nagar", "name_hi": "खीवसिंह नगर" },
    { "name": "Khudiyala", "name_hi": "खुडियाला" },
    { "name": "Kinjari", "name_hi": "किंजारी" },
    { "name": "Kiram Sariya Kalan", "name_hi": "किरमसरिया कलां" },
    { "name": "Kiramsariya Khurd", "name_hi": "किरमसरिया खुर्द" },
    { "name": "Kotra", "name_hi": "कोटड़ा" },
    { "name": "Lakheta", "name_hi": "लखेता" },
    { "name": "Lal Sagar", "name_hi": "लाल सागर" },
    { "name": "Laxmi Narayan Nagar", "name_hi": "लक्ष्मी नारायण नगर" },
    { "name": "Magra Nagar", "name_hi": "मागरा नगर" },
    { "name": "Mahadev Nagar", "name_hi": "महादेव नगर" },
    { "name": "Mahadev Nagar (Morali Bari)", "name_hi": "महादेव नगर (मोरली बाड़ी)" },
    { "name": "Maloonga", "name_hi": "मालूंगा" },
    { "name": "Mandiyai Kalan", "name_hi": "मंडियाई कलां" },
    { "name": "Mandiyai Khurd", "name_hi": "मंडियाई खुर्द" },
    { "name": "Mansagar", "name_hi": "मानसागर" },
    { "name": "Mathaniya", "name_hi": "मथानिया" },
    { "name": "Matora", "name_hi": "मटोर" },
    { "name": "Meeno Ki Dhani", "name_hi": "मीणों की ढाणी" },
    { "name": "Meha Nagar", "name_hi": "मेहा नगर" },
    { "name": "Mepan", "name_hi": "मेपान" },
    { "name": "Mewasa", "name_hi": "मेवासा" },
    { "name": "Motaniya Nagar", "name_hi": "मोतानिया नगर" },
    { "name": "Muknasar", "name_hi": "मुखनासर" },
    { "name": "Nageshwar Nagar", "name_hi": "नागेश्वर नगर" },
    { "name": "Nandiya Jajra", "name_hi": "नांदिया जाजरा" },
    { "name": "Nandiya Kalan", "name_hi": "नांदिया कलां" },
    { "name": "Nandiya Khurd", "name_hi": "नांदिया खुर्द" },
    { "name": "Nari Nadi", "name_hi": "नाड़ी नदी" },
    { "name": "Narsingh Nagar", "name_hi": "नरसिंह नगर" },
    { "name": "Nathawat Nagar", "name_hi": "नाथावत नगर" },
    { "name": "Nausar", "name_hi": "नौसर" },
    { "name": "Nerwa Charnan", "name_hi": "नेरवा चारणन" },
    { "name": "Newra", "name_hi": "नेवरा" },
    { "name": "Newra Road", "name_hi": "नेवरा रोड" },
    { "name": "Nimbla", "name_hi": "निंबला" },
    { "name": "Nimbli Bera", "name_hi": "निंबली बेरा" },
    { "name": "Nimbonka Talab", "name_hi": "निंबों का तालाब" },
    { "name": "Ompura", "name_hi": "ओमपुरा" },
    { "name": "Osian", "name_hi": "ओसियां" },
    { "name": "P S Nagar", "name_hi": "पी.एस. नगर" },
    { "name": "Pabu Nagar", "name_hi": "पाबू नगर" },
    { "name": "Pabunagar", "name_hi": "पाबूनगर" },
    { "name": "Pali- I", "name_hi": "पाली- I" },
    { "name": "Pali-Ii", "name_hi": "पाली- II" },
    { "name": "Palli", "name_hi": "पाली" },
    { "name": "Panchla Khurd", "name_hi": "पांचला खुर्द" },
    { "name": "Panditji Ki Dhani", "name_hi": "पंडितजी की ढाणी" },
    { "name": "Parasala", "name_hi": "परसाला" },
    { "name": "Peepasar Nagar", "name_hi": "पीपासर नगर" },
    { "name": "Peethasar", "name_hi": "पीठासर" },
    { "name": "Poonasar", "name_hi": "पूणासर" },
    { "name": "Poonasar Khurd", "name_hi": "पूणासर खुर्द" },
    { "name": "Pratapnagar", "name_hi": "प्रतापनगर" },
    { "name": "Prem Nagar", "name_hi": " प्रेम नगर" },
    { "name": "Puniyon Ki Dhani", "name_hi": "पूनियों की ढाणी" },
    { "name": "Radiya Bera", "name_hi": "राड़िया बेरा" },
    { "name": "Raikoriya", "name_hi": "रैकौरिया" },
    { "name": "Raimalwara", "name_hi": "रैमलवाड़ा" },
    { "name": "Rajasani", "name_hi": "राजासनी" },
    { "name": "Ram Nagar", "name_hi": "राम नगर" },
    { "name": "Ramdeora Rajasani", "name_hi": "रामदेवरा राजासनी" },
    { "name": "Ramdev Nagar", "name_hi": "रामदेव नगर" },
    { "name": "Ramgarh", "name_hi": "रामगढ़" },
    { "name": "Ramnagar", "name_hi": "रामनगर" },
    { "name": "Rampura Bhatiya", "name_hi": "रामपुरा भाटिया" },
    { "name": "Rawal Nagar", "name_hi": "रावल नगर" },
    { "name": "Rawat Nagar", "name_hi": "रावत नगर" },
    { "name": "Relagarh", "name_hi": "रेलागढ़" },
    { "name": "Rewantsingh Nagar", "name_hi": "रेवंतसिंह नगर" },
    { "name": "Riniya", "name_hi": "रीनिया" },
    { "name": "Roop Nagar", "name_hi": "रूप नगर" },
    { "name": "Samrathalnagar", "name_hi": "समराथल नगर" },
    { "name": "Samrau", "name_hi": "समराउ" },
    { "name": "Sant Kriparam Nagar", "name_hi": "संत कृपाराम नगर" },
    { "name": "Sant Sri Nimbaram Nagar", "name_hi": "संत श्री निम्बाराम नगर" },
    { "name": "Santora Kalan", "name_hi": "संतोरा कलां" },
    { "name": "Santora Khurd", "name_hi": "संतोरा खुर्द" },
    { "name": "Sanwata", "name_hi": "सांवता" },
    { "name": "Saran Nagar", "name_hi": "सरन नगर" },
    { "name": "Saraswati Nagar", "name_hi": "सरस्वती नगर" },
    { "name": "Shiv Nagar", "name_hi": "शिव नगर" },
    { "name": "Shiv Sagar", "name_hi": "शिव सागर" },
    { "name": "Shivnagar", "name_hi": "शिवनगर" },
    { "name": "Shri Ramdev Nagar", "name_hi": "श्री रामदेव नगर" },
    { "name": "Sili", "name_hi": "सिली" },
    { "name": "Simrath Nagar", "name_hi": "सिमरथ नगर" },
    { "name": "Sindhiyon Ki Dhani", "name_hi": "सिन्धियों की ढाणी" },
    { "name": "Sirmandi", "name_hi": "सिरमंडी" },
    { "name": "Sou & Bhambhoon Ki Dhaniyan", "name_hi": "सौ एवं भंभूओं की ढाणियां" },
    { "name": "Sri Karnipura", "name_hi": "श्री करणीपुरा" },
    { "name": "Sri Ramdeo Nagar", "name_hi": "श्री रामदेव नगर" },
    { "name": "Sri Sangiyaji Nagar", "name_hi": "श्री सांगीयाजी नगर" },
    { "name": "Swami Umagiriji Ki Dhani", "name_hi": "स्वामी उमागिरीजी की ढाणी" },
    { "name": "Taaj Nagar", "name_hi": "ताज नगर" },
    { "name": "Tapoo", "name_hi": "तापू" },
    { "name": "Teja Nagar", "name_hi": "तेजा नगर" },
    { "name": "Thob", "name_hi": "थोब" },
    { "name": "Tiwari", "name_hi": "तिवाड़ी" },
    { "name": "Ujaliya", "name_hi": "उजालिया" },
    { "name": "Umadesar", "name_hi": "उमादेसर" },
    { "name": "Ummednagar", "name_hi": "उम्मेदनगर" },
    { "name": "Unawara", "name_hi": "उणावरा" },
    { "name": "Veer Durgadas Nagar", "name_hi": "वीर दुर्गादास नगर" },
    { "name": "Veer Teja Ji Nagar", "name_hi": "वीर तेजाजी नगर" },
    { "name": "Veerteja Nagar", "name_hi": "वीरतेजा नगर" },
    { "name": "Vinayakpura", "name_hi": "विनायकपुरा" },
    { "name": "Vishnu Ki Dhani", "name_hi": "विष्णु की ढाणी" },
    { "name": "Vishnu Nagar", "name_hi": "विष्णु नगर" },
    { "name": "Vishnu Nagar (Khetasar)", "name_hi": "विष्णु नगर (खेड़ासर)" },
    { "name": "Vishvakarma Nagar", "name_hi": "विश्वकर्मा नगर" }
  ]
}
,
   {
  "tehsil": "Phalodi",
  "villages": [
    { "name": "Aaseji Nagar", "name_hi": "आसेजी नगर" },
    { "name": "Aau", "name_hi": "आऊ" },
    { "name": "Ahopnagar", "name_hi": "अहोप नगर" },
    { "name": "Ajasar", "name_hi": "अजासर" },
    { "name": "Ajeri", "name_hi": "अजेरी" },
    { "name": "Akhadhana", "name_hi": "अखाधाना" },
    { "name": "Amarpura", "name_hi": "अमरपुरा" },
    { "name": "Ambadkar Nagar", "name_hi": "अम्बेडकर नगर" },
    { "name": "Amla", "name_hi": "आमला" },
    { "name": "Andara Nada", "name_hi": "अंदारा नाड़ा" },
    { "name": "Anjanisar", "name_hi": "अंजनीसर" },
    { "name": "Arandiyan", "name_hi": "अरंडीयन" },
    { "name": "Asolai", "name_hi": "आसोलाई" },
    { "name": "Aundasar", "name_hi": "औंदासर" },
    { "name": "Baba Ka Dhora", "name_hi": "बाबा का धोरा" },
    { "name": "Baba Nagar", "name_hi": "बाबा नगर" },
    { "name": "Baba Ramdeo Nagari", "name_hi": "बाबा रामदेव नगरी" },
    { "name": "Bagda", "name_hi": "बागड़ा" },
    { "name": "Bagdawat Nagar", "name_hi": "बागड़ावत नगर" },
    { "name": "Bagga", "name_hi": "बग्गा" },
    { "name": "Baghaura", "name_hi": "बघौरा" },
    { "name": "Bagji Ka Paar", "name_hi": "बगजी का पार" },
    { "name": "Bagtawar Nagar", "name_hi": "बागटावर नगर" },
    { "name": "Bajrang Nagar", "name_hi": "बजरंग नगर" },
    { "name": "Balasar", "name_hi": "बालासर" },
    { "name": "Bamnoo", "name_hi": "बामनू" },
    { "name": "Bamnoo Khurd", "name_hi": "बामनू खुर्द" },
    { "name": "Bandheri", "name_hi": "बांधेरी" },
    { "name": "Banesinghpura", "name_hi": "बनेसिंहपुरा" },
    { "name": "Banswara Nagar", "name_hi": "बांसवाड़ा नगर" },
    { "name": "Baori Barsinga", "name_hi": "बावड़ी बारसिंगा" },
    { "name": "Baori Kalan", "name_hi": "बावड़ी कलां" },
    { "name": "Baori Khurd", "name_hi": "बावड़ी खुर्द" },
    { "name": "Bap", "name_hi": "बाप" },
    { "name": "Bapinee", "name_hi": "बापीनी" },
    { "name": "Bari Dhani", "name_hi": "बड़ी ढाणी" },
    { "name": "Bari Seer", "name_hi": "बड़ी सीर" },
    { "name": "Barjasar", "name_hi": "बरजासर" },
    { "name": "Baroo", "name_hi": "बरू" },
    { "name": "Barsingon Ka Bas", "name_hi": "बारसिंगों का बास" },
    { "name": "Baya Nagar", "name_hi": "बाया नगर" },
    { "name": "Beegasar", "name_hi": "बीगासर" },
    { "name": "Beethri", "name_hi": "बीथरी" },
    { "name": "Begti Kalan", "name_hi": "बेगटी कलां" },
    { "name": "Begti Khurd", "name_hi": "बेगटी खुर्द" },
    { "name": "Bhadlachuhron Ki Basti", "name_hi": "भादला चूहड़ो की बस्ती" },
    { "name": "Bhadu Nagar", "name_hi": "भाडू नगर" },
    { "name": "Bhagwan Nagar", "name_hi": "भगवान नगर" },
    { "name": "Bhajan Nagar", "name_hi": "भजन नगर" },
    { "name": "Bhakhariya", "name_hi": "भाखड़िया" },
    { "name": "Bhatiyon Ki Dhani", "name_hi": "भाटियों की ढाणी" },
    { "name": "Bhayyon Ki Dhani", "name_hi": "भैयों की ढाणी" },
    { "name": "Bheem Sagar", "name_hi": "भीम सागर" },
    { "name": "Bheemji Ka Gaon", "name_hi": "भीमजी का गांव" },
    { "name": "Bheeyasar", "name_hi": "भीयसार" },
    { "name": "Bhoj Nagar", "name_hi": "भोज नगर" },
    { "name": "Bhoja Kor", "name_hi": "भोजा कोर" },
    { "name": "Bhoja Nagar", "name_hi": "भोजा नगर" },
    { "name": "Bhojasar", "name_hi": "भोजासर" },
    { "name": "Bhojka", "name_hi": "भोजका" },
    { "name": "Bhojon Ki Bap Chak No1-2", "name_hi": "भोजन की बाप चक नं. 1-2" },
    { "name": "Bhom Nagar", "name_hi": "भौम नगर" },
    { "name": "Bhomji Ka Gaon", "name_hi": "भोमजी का गांव" },
    { "name": "Bilhoji Nagar", "name_hi": "बिल्होजी नगर" },
    { "name": "Bohranada", "name_hi": "बोहरानाडा" },
    { "name": "Bombapura", "name_hi": "बोम्बापुरा" },
    { "name": "Boogdi", "name_hi": "बूगड़ी" },
    { "name": "Chadi", "name_hi": "छड़ी" },
    { "name": "Chainpura", "name_hi": "चैनपुरा" },
    { "name": "Chainpura Kalan", "name_hi": "चैनपुरा कलां" },
    { "name": "Chakhu", "name_hi": "चाखू" },
    { "name": "Champasar", "name_hi": "चम्पासर" },
    { "name": "Champawat Nagar", "name_hi": "चम्पावत नगर" },
    { "name": "Chandra Nagar", "name_hi": "चन्द्र नगर" },
    { "name": "Charnai", "name_hi": "चारनाई" },
    { "name": "Chatala Nagar", "name_hi": "चटाला नगर" },
    { "name": "Chauhano Ka Bera", "name_hi": "चौहानों का बेरा" },
    { "name": "Cheemana", "name_hi": "चीमना" },
    { "name": "Chhaino Ki Dhani", "name_hi": "छैनो की ढाणी" },
    { "name": "Chhatarwalon Ka Gaon", "name_hi": "छत्तरवालों का गांव" },
    { "name": "Chheela", "name_hi": "छेला" },
    { "name": "Chheelasar", "name_hi": "छीलासर" },
    { "name": "Chhila Nadi", "name_hi": "छीला नदी" },
    { "name": "Chhitar Bera", "name_hi": "छीतर बेरा" },
    { "name": "Chikni Nari", "name_hi": "चिकनी नाड़ी" },
    { "name": "Chiri", "name_hi": "चिरी" },
    { "name": "Chutar Nagar", "name_hi": "चूतर नगर" },
    { "name": "Dabar", "name_hi": "डाबर" },
    { "name": "Dadu Dayal Nagar", "name_hi": "दादू दयाल नगर" },
    { "name": "Dalji Ki Dhani", "name_hi": "दलजी की ढाणी" },
    { "name": "Daya Kor", "name_hi": "दयाकोर" },
    { "name": "Daya Sagar", "name_hi": "दया सागर" },
    { "name": "Dedasari", "name_hi": "डेडासरी" },
    { "name": "Dedisara", "name_hi": "डेडीसरा" },
    { "name": "Dediya", "name_hi": "डेडिया" },
    { "name": "Deep Nagar", "name_hi": "दीप नगर" },
    { "name": "Deepawat Nagar", "name_hi": "दीपावत नगर" },
    { "name": "Degawari", "name_hi": "देगावड़ी" },
    { "name": "Deiramangar", "name_hi": "देवराम नगर" },
    { "name": "Denok", "name_hi": "देनोक" },
    { "name": "Deo Nagar", "name_hi": "देव नगर" },
    { "name": "Deoli Jaal", "name_hi": "देओली जाल" },
    { "name": "Deoli Nagar", "name_hi": "देओली नगर" },
    { "name": "Deraj Nagar", "name_hi": "डेराज नगर" },
    { "name": "Deriyon Ki Dhani", "name_hi": "डेरियों की ढाणी" },
    { "name": "Dev Nagari", "name_hi": "देव नगरी" },
    { "name": "Devdo Ki Dhani", "name_hi": "देवड़ो की ढाणी" },
    { "name": "Devi Nagar", "name_hi": "देवी नगर" },
    { "name": "Dhadharwala", "name_hi": "धाधरवाला" },
    { "name": "Dhadho", "name_hi": "ढाढो" },
    { "name": "Dhakanagar Lohawat", "name_hi": "ढाका नगर लोहार" },
    { "name": "Dhaksene Dhani Ranisar", "name_hi": "धाकसेणे ढाणी रानीसर" },
    { "name": "Dhaneshwar Nagar Purohitan", "name_hi": "धनेश्वर नगर पुरोहितान" },
    { "name": "Dhara Bagapuran", "name_hi": "धारा बगापुरा" },
    { "name": "Dharo Ki Dhani", "name_hi": "धारो की ढाणी" },
    { "name": "Dhelana", "name_hi": "ढेलाना" },
    { "name": "Dhokal Nagar", "name_hi": "धोकल नगर" },
    { "name": "Dholasar", "name_hi": "धोलासर" },
    { "name": "Dholiya", "name_hi": "धोलिया" },
    { "name": "Duda Nagar", "name_hi": "दूडा नगर" },
    { "name": "Dudi Nagar @ Bhakti Nagar", "name_hi": "डूडी नगर @ भक्ति नगर" },
    { "name": "Dumaderi(Khanpur)", "name_hi": "दुमादेरी (खानपुर)" },
    { "name": "Durgani", "name_hi": "दुर्गाणी" },
    { "name": "Durjani", "name_hi": "दुर्जनी" },
    { "name": "Eka Bhatiyan", "name_hi": "एका भाटीयान" },
    { "name": "Ekal Thali", "name_hi": "एकल थली" },
    { "name": "Fateh Nagar", "name_hi": "फतेह नगर" },
    { "name": "Fateh Sagar", "name_hi": "फतेह सागर" },
    { "name": "Gadna", "name_hi": "गड़ना" },
    { "name": "Gaiya Nagar", "name_hi": "गैया नगर" },
    { "name": "Gaiyo Ki Dhani", "name_hi": "गैयो की ढाणी" },
    { "name": "Gajja", "name_hi": "गज्जा" },
    { "name": "Gandhi Nagar", "name_hi": "गांधी नगर" },
    { "name": "Gandhi Sagar", "name_hi": "गांधी सागर" },
    { "name": "Ganesh Nagar", "name_hi": "गणेश नगर" },
    { "name": "Ganeshpur", "name_hi": "गणेशपुर" },
    { "name": "Ghamadaniyon Ki Dhani", "name_hi": "घमड़ानियों की ढाणी" },
    { "name": "Ghamner", "name_hi": "घमनेर" },
    { "name": "Ghantiyali", "name_hi": "घंटियाली" },
    { "name": "Ghator", "name_hi": "घाटोर" },
    { "name": "Godana", "name_hi": "गोदाना" },
    { "name": "Godarli", "name_hi": "गोदारली" },
    { "name": "Gopa", "name_hi": "गोपा" },
    { "name": "Gorchiya Ka Bera", "name_hi": "गोरचिया का बेरा" },
    { "name": "Gosai Ji Ka Dhora", "name_hi": "गोसायजी का धोरा" },
    { "name": "Gosaipura", "name_hi": "गोसाईपुरा" },
    { "name": "Govind Nagar", "name_hi": "गोविन्द नगर" },
    { "name": "Gurha", "name_hi": "गुर्हा" },
    { "name": "Hansa Desh", "name_hi": "हंसा देश" },
    { "name": "Hanuman Nagar", "name_hi": "हनुमान नगर" },
    { "name": "Hanuman Sagar", "name_hi": "हनुमान सागर" },
    { "name": "Hanumanpura", "name_hi": "हनुमानपुरा" },
    { "name": "Hanvant Nagar", "name_hi": "हणवंत नगर" },
    { "name": "Hari Pura", "name_hi": "हरिपुरा" },
    { "name": "Harisingh Nagar", "name_hi": "हरीसिंह नगर" },
    { "name": "Hasampura", "name_hi": "हसनपुरा" },
    { "name": "Hazi Nagar", "name_hi": "हाजी नगर" },
    { "name": "Hazi Sagar", "name_hi": "हाजी सागर" },
    { "name": "Hazipura", "name_hi": "हाजीपुरा" },
    { "name": "Heera Moti Nagar", "name_hi": "हीरा मोती नगर" },
    { "name": "Hemraj Nagar", "name_hi": "हेमराज नगर" },
    { "name": "Himat Nagar", "name_hi": "हिम्मत नगर" },
    { "name": "Himmat Nagar", "name_hi": "हिम्मतनगर" },
    { "name": "Hindal Gol", "name_hi": "हिन्दाल गोल" },
    { "name": "Hopardi", "name_hi": "होपर्दी" },
    { "name": "Imam Nagar", "name_hi": "इमाम नगर" },
    { "name": "Indon Ka Bas", "name_hi": "इंदों का बास" },
    { "name": "Indra Nagar", "name_hi": "इन्द्रा नगर" },
    { "name": "Ishru", "name_hi": "इश्रु" },
    { "name": "Ismile Khan Ki Dhani", "name_hi": "इस्माइल खान की ढाणी" },
    { "name": "Jagariya", "name_hi": "जागड़िया" },
    { "name": "Jagramsar", "name_hi": "जाग्रामसर" },
    { "name": "Jagu Bana Ki Dhani", "name_hi": "जगू बाना की ढाणी" },
    { "name": "Jaimala", "name_hi": "जयमाला" },
    { "name": "Jaisala", "name_hi": "जैसला" },
    { "name": "Jaisingh Nagar", "name_hi": "जैसिंह नगर" },
    { "name": "Jaitrasar", "name_hi": "जैत्रासर" },
    { "name": "Jaldara", "name_hi": "जलदड़ा" },
    { "name": "Jalora", "name_hi": "जलोरा" },
    { "name": "Jamba", "name_hi": "जाम्बा" },
    { "name": "Jamba Ki Dhani", "name_hi": "जाम्बा की ढाणी" },
    { "name": "Jambheshvar Nagari", "name_hi": "जांभेश्वर नगरी" },
    { "name": "Jambh Nagar", "name_hi": "जांभ नगर" },
    { "name": "Jambh Sagar", "name_hi": "जांभ सागर" },
    { "name": "Jambheswar Nagar-Ii", "name_hi": "जांभेश्वर नगर-II" },
    { "name": "Jambhshakti Nagar", "name_hi": "जांभशक्ति नगर" },
    { "name": "Jangu Nagar", "name_hi": "जंगू नगर" },
    { "name": "Janupura", "name_hi": "जनूपुरा" },
    { "name": "Jatisara", "name_hi": "जाटीसरा" },
    { "name": "Jawar Nada", "name_hi": "जावर नाड़ा" },
    { "name": "Jesari", "name_hi": "जेसरी" },
    { "name": "Jharasar", "name_hi": "झारासर" },
    { "name": "Jhardeji Ki Bhakri", "name_hi": "झाड़ेजी की भाखरी" },
    { "name": "Jodhani @ Tepoo", "name_hi": "जोधाणी @ टेपु" },
    { "name": "Jor", "name_hi": "जोर" },
    { "name": "Jorawar Nagar", "name_hi": "जोरावर नगर" },
    { "name": "Junejo Ki Dhani", "name_hi": "जूनेजो की ढाणी" },
    { "name": "Kacholiya Nada", "name_hi": "कचोलिया नाड़ा" },
    { "name": "Kalathal", "name_hi": "कलेठल" },
    { "name": "Kali Mali", "name_hi": "काली माली" },
    { "name": "Kalirananagar", "name_hi": "कलिराणा नगर" },
    { "name": "Kalran", "name_hi": "कलरान" },
    { "name": "Kalrawa Bera", "name_hi": "कलरावा बेरा" },
    { "name": "Kalu Kha Ki Dhani", "name_hi": "कालू खां की ढाणी" },
    { "name": "Kalusingh Nagar", "name_hi": "कालूसिंह नगर" },
    { "name": "Kalyan Singh Ki Seer", "name_hi": "कल्याण सिंह की सीर" },
    { "name": "Kalyanpura", "name_hi": "कल्याणपुरा" },
    { "name": "Kamardin Ki Basti", "name_hi": "कमरुद्दीन की बस्ती" },
    { "name": "Kanasar", "name_hi": "कनासर" },
    { "name": "Kanasariya", "name_hi": "कनासरिया" },
    { "name": "Kanasi Moti", "name_hi": "कनासी मोती" },
    { "name": "Kansingh Ki Seer", "name_hi": "कनसिंह की सीर" },
    { "name": "Kapdisar", "name_hi": "कपड़ीसर" },
    { "name": "Karani Pura", "name_hi": "करणीपुरा" },
    { "name": "Karmana Nagar", "name_hi": "कर्माना नगर" },
    { "name": "Karni Nagar", "name_hi": "करणी नगर" },
    { "name": "Karninagar", "name_hi": "करणीनगर" },
    { "name": "Kaushal Nagar", "name_hi": "कौशल नगर" },
    { "name": "Kelan Nagar", "name_hi": "केलन नगर" },
    { "name": "Kelansar", "name_hi": "केलांसर" },
    { "name": "Kerla", "name_hi": "केरला" },
    { "name": "Keshar Pura", "name_hi": "केशरपुरा" },
    { "name": "Keshav Nagar", "name_hi": "केशव नगर" },
    { "name": "Khajoosar", "name_hi": "खाजूसर" },
    { "name": "Khakhuri", "name_hi": "खाखुरी" },
    { "name": "Khara", "name_hi": "खारा" },
    { "name": "Khariya", "name_hi": "खारिया" },
    { "name": "Khariya Kansingh", "name_hi": "खारिया कानसिंह" },
    { "name": "Khavo Ki Dhani Ranisar", "name_hi": "खावो की ढाणी रानीसर" },
    { "name": "Kheechan", "name_hi": "खींचन" },
    { "name": "Kheerwa", "name_hi": "खीरवा" },
    { "name": "Khenchado Ki Dhani", "name_hi": "खेंचड़ो की ढाणी" },
    { "name": "Khengasar", "name_hi": "खेंगासर" },
    { "name": "Khera Bagoriya", "name_hi": "खेड़ा बगोरिया" },
    { "name": "Khetusar", "name_hi": "खेथूसर" },
    { "name": "Khidrat", "name_hi": "खिदरात" },
    { "name": "Kishan Nagar", "name_hi": "किशन नगर" },
    { "name": "Kishanpura", "name_hi": "किशनपुरा" },
    { "name": "Kishnari Jeti", "name_hi": "किशनड़ी जेती" },
    { "name": "Kodiya Nada", "name_hi": "कोड़िया नाड़ा" },
    { "name": "Koloo Pabuji", "name_hi": "कोलू पाबूजी" },
    { "name": "Kolu Nimbavata", "name_hi": "कोलू निंबावता" },
    { "name": "Kolu Rathoron", "name_hi": "कोलू राठौड़न" },
    { "name": "Kotecho Ki Dhani", "name_hi": "कोटेको की ढाणी" },
    { "name": "Krishan Nagar Kalan", "name_hi": "कृष्णा नगर कलां" },
    { "name": "Kuknon Ki Dhani", "name_hi": "कुकनौं की ढाणी" },
    { "name": "Kundal", "name_hi": "कुंडल" },
    { "name": "Kushalaram Ki Basti", "name_hi": "कुशलाराम की बस्ती" },
    { "name": "Kushlawa", "name_hi": "कुशलावा" },
    { "name": "Laxmanpura", "name_hi": "लक्ष्मणपुरा" },
    { "name": "Laxmi Nagar", "name_hi": "लक्ष्मी नगर" },
    { "name": "Likhmasar", "name_hi": "लिखमासर" },
    { "name": "Lohawat Bisnawas", "name_hi": "लोहावट बिसनावास" },
    { "name": "Lohawat Jatahwas", "name_hi": "लोहावट जतहवास" },
    { "name": "Lokayat", "name_hi": "लोकायत" },
    { "name": "Lordiyan", "name_hi": "लोरड़ीयन" },
    { "name": "Lukkupura @ Asraf Nagar", "name_hi": "लुक्कूपुरा @ अशरफ नगर" },
    { "name": "Lumbaniya", "name_hi": "लुम्बानिया" },
    { "name": "Lumbasar", "name_hi": "लुम्बासर" },
    { "name": "Luna", "name_hi": "लूणा" },
    { "name": "Madla Kalan", "name_hi": "मड़ला कलां" },
    { "name": "Madla Khurd", "name_hi": "मड़ला खुर्द" },
    { "name": "Madpura", "name_hi": "मदपुरा" },
    { "name": "Madrup Nagar", "name_hi": "मद्रूप नगर" },
    { "name": "Maghasar", "name_hi": "माघासर" },
    { "name": "Magra", "name_hi": "मागरा" },
    { "name": "Maha Sati Nagar", "name_hi": "महा सती नगर" },
    { "name": "Mahadeo Nagar", "name_hi": "महादेव नगर" },
    { "name": "Mahadeopura", "name_hi": "महादेओपुरा" },
    { "name": "Mahirshi Gotam Nagar", "name_hi": "महर्षि गौतम नगर" },
    { "name": "Malamsingh Ki Seer", "name_hi": "मालमसिंह की सीर" },
    { "name": "Malar", "name_hi": "मालर" },
    { "name": "Mananavar", "name_hi": "मननावर" },
    { "name": "Manasar", "name_hi": "मनासर" },
    { "name": "Manchitiya", "name_hi": "मंचीतिया" },
    { "name": "Mandli", "name_hi": "मंडली" },
    { "name": "Mandor ( Dara Ka Bas)", "name_hi": "मंडोर (दारा का बास)" },
    { "name": "Maneora", "name_hi": "मानेओरा" },
    { "name": "Mangal Nagar", "name_hi": "मंगल नगर" },
    { "name": "Manju Nagar", "name_hi": "मंजू नगर" },
    { "name": "Manpura Lohawat", "name_hi": "मानपुरा लोहावट" },
    { "name": "Mashala", "name_hi": "मसाला" },
    { "name": "Masjid Wali Dhani", "name_hi": "मस्जिद वाली ढाणी" },
    { "name": "Mataji Ki Doli", "name_hi": "माताजी की डोली" },
    { "name": "Matol", "name_hi": "मटोल" },
    { "name": "Matol Chak", "name_hi": "मटोल चक" },
    { "name": "Matol Tanka", "name_hi": "मटोल टांका" },
    { "name": "Maya Koriya", "name_hi": "माया कोरिया" },
    { "name": "Mayakor", "name_hi": "मायाकोर" },
    { "name": "Meer Nagar", "name_hi": "मीर नगर" },
    { "name": "Meethadiya", "name_hi": "मीठड़िया" },
    { "name": "Megwalon Ki Dhani", "name_hi": "मेघवालों की ढाणी" },
    { "name": "Meharam Nagar", "name_hi": "मेहराम नगर" },
    { "name": "Modkiya", "name_hi": "मोदकिया" },
    { "name": "Mohar Nagar", "name_hi": "मोहर नगर" },
    { "name": "Moharsar", "name_hi": "मोहरसर" },
    { "name": "Mohra", "name_hi": "मोहरा" },
    { "name": "Mokheri", "name_hi": "मोखड़ी" },
    { "name": "Moolraj", "name_hi": "मूलराज" },
    { "name": "Moriya", "name_hi": "मोरिया" },
    { "name": "Motai", "name_hi": "मोताई" },
    { "name": "Moti Nagar", "name_hi": "मोती नगर" },
    { "name": "Munjasar", "name_hi": "मूंजासर" },
    { "name": "Nagnechinagar", "name_hi": "नगनेची नगर" },
    { "name": "Naneu", "name_hi": "ननेऊ" },
    { "name": "Narayan Hari", "name_hi": "नारायण हरी" },
    { "name": "Narayan Nagar", "name_hi": "नारायण नगर" },
    { "name": "Narayanpura", "name_hi": "नारायणपुरा" },
    { "name": "Narsingh Nagar", "name_hi": "नरसिंह नगर" },
    { "name": "Nath Ka Magra", "name_hi": "नाथ का मगरा" },
    { "name": "Navneetpura", "name_hi": "नवनीतपुरा" },
    { "name": "Naya Bera", "name_hi": "नया बेरा" },
    { "name": "Naya Gaon", "name_hi": "नया गांव" },
    { "name": "Neda Nagar Lohawat", "name_hi": "नेड़ा नगर लोहावट" },
    { "name": "Netaji Nagar", "name_hi": "नेताजी नगर" },
    { "name": "Newa", "name_hi": "नेवा" },
    { "name": "Nijamdin Ki Basti", "name_hi": "निजामदीन की बस्ती" },
    { "name": "Nokhra Bhatiyan", "name_hi": "नोखड़ा भाटीयान" },
    { "name": "Nokhra Charna", "name_hi": "नोखड़ा चारण" },
    { "name": "Nokhra Godara", "name_hi": "नोखड़ा गोदारा" },
    { "name": "Nokhra Patawatan", "name_hi": "नोखड़ा पातावातन" },
    { "name": "Noore Ki Burj", "name_hi": "नूरें की बुर्ज" },
    { "name": "Pabdo Ki Dhani Likhamsar", "name_hi": "पाबडो की ढाणी लिखमसर" },
    { "name": "Paboo Chhawara", "name_hi": "पाबू छवाड़ा" },
    { "name": "Pabu Nagar", "name_hi": "पाबू नगर" },
    { "name": "Pabuji Nagar", "name_hi": "पाबूजी नगर" },
    { "name": "Pabupura", "name_hi": "पाबूपुरा" },
    { "name": "Pabusar", "name_hi": "पाबूसर" },
    { "name": "Padmet Nagar", "name_hi": "पद्मेत नगर" },
    { "name": "Paleena", "name_hi": "पलीना" },
    { "name": "Panna Nagar", "name_hi": "पन्ना नगर" },
    { "name": "Pariyal", "name_hi": "परियाल" },
    { "name": "Pashchimi Dhani", "name_hi": "पश्चिमी ढाणी" },
    { "name": "Peelwa", "name_hi": "पीलवा" },
    { "name": "Phalodi (M + OG)", "name_hi": "फालोदी (नगर + बाह्य क्षेत्र)" },
    { "name": "Phalodi (Rural)", "name_hi": "फालोदी (ग्रामीण)" },
    { "name": "Pipaliya Nagar", "name_hi": "पिपल्या नगर" },
    { "name": "Pratap Nagar", "name_hi": "प्रताप नगर" },
    { "name": "Prem Nagar", "name_hi": "प्रेम नगर" },
    { "name": "Prithviraj Singh Nagar", "name_hi": "पृथ्वीराज सिंह नगर" },
    { "name": "Pulaniyon Ki Dhani", "name_hi": "पुलानियों की ढाणी" },
    { "name": "Radka Pura", "name_hi": "रडकापुरा" },
    { "name": "Rahimpura", "name_hi": "रहीमपुरा" },
    { "name": "Raika Bagh", "name_hi": "राइका बाग" },
    { "name": "Rajala", "name_hi": "राजाला" },
    { "name": "Rajeev Nagar", "name_hi": "राजीव नगर" },
    { "name": "Ram Nagar", "name_hi": "राम नगर" },
    { "name": "Ram Sagar", "name_hi": "राम सागर" },
    { "name": "Ram Shakti Nagar", "name_hi": "राम शक्ति नगर" },
    { "name": "Ramcheema Nada", "name_hi": "रामचीमा नाड़ा" },
    { "name": "Ramdeo Nagar", "name_hi": "रामदेव नगर" },
    { "name": "Ramdeopura", "name_hi": "रामदेवपुरा" },
    { "name": "Ramdev Nagar", "name_hi": "रामदेव नगर" },
    { "name": "Ramjan Pura", "name_hi": "रामजानपुरा" },
    { "name": "Ramnagar", "name_hi": "रामनगर" },
    { "name": "Ramnagar Denok", "name_hi": "रामनगर देनोक" },
    { "name": "Rampura", "name_hi": "रामपुरा" },
    { "name": "Raneri", "name_hi": "रानेरी" },
    { "name": "Ranisar", "name_hi": "रानीसर" },
    { "name": "Ranjeet Nagar", "name_hi": "रंजीत नगर" },
    { "name": "Rawat Nagar", "name_hi": "रावत नगर" },
    { "name": "Rawra", "name_hi": "रावरा" },
    { "name": "Rayra", "name_hi": "रायरा" },
    { "name": "Reen", "name_hi": "रीन" },
    { "name": "Ridmal Nagar", "name_hi": "रिड़मल नगर" },
    { "name": "Ridmalnagar Kalan", "name_hi": "रिड़मलनगर कलां" },
    { "name": "Ridmalsar", "name_hi": "रिड़मलसर" },
    { "name": "Rode Ji Ki Dhani", "name_hi": "रोड़े जी की ढाणी" },
    { "name": "Rohida Nagar", "name_hi": "रोहीड़ा नगर" },
    { "name": "Rohina", "name_hi": "रोहीणा" },
    { "name": "Rola", "name_hi": "रोला" },
    { "name": "Roopana Jaitana", "name_hi": "रूपणा जैताना" },
    { "name": "Rugnathpura", "name_hi": "रूगनाथपुरा" },
    { "name": "Saathri Ki Dhaniya", "name_hi": "साठरी की ढाणियां" },
    { "name": "Sabalsar Lohawat", "name_hi": "सबंलसर लोहावट" },
    { "name": "Sadawata", "name_hi": "सदावट" },
    { "name": "Sadri", "name_hi": "सादड़ी" },
    { "name": "Sadri Khurd", "name_hi": "सादड़ी खुर्द" },
    { "name": "Saheed Mohanram Nagar", "name_hi": "शहीद मोहनराम नगर" },
    { "name": "Sai Nagar", "name_hi": "साईं नगर" },
    { "name": "Sajan Nagar", "name_hi": "साजन नगर" },
    { "name": "Sajnaniyon Ki Dhani", "name_hi": "सज्नानियों की ढाणी" },
    { "name": "Salasar", "name_hi": "सलासर" },
    { "name": "Samlani Nagar", "name_hi": "सम्लानी नगर" },
    { "name": "Samrathalpura", "name_hi": "समराथलपुरा" },
    { "name": "Sanguri", "name_hi": "सांगुरी" },
    { "name": "Santok Nagar", "name_hi": "संतोक नगर" },
    { "name": "Sanwal Nagar", "name_hi": "सांवळ नगर" },
    { "name": "Sanwara Gaon", "name_hi": "सांवरा गांव" },
    { "name": "Sanwatsar", "name_hi": "सांवतसर" },
    { "name": "Sanwreej", "name_hi": "सांव्रीज" },
    { "name": "Saranpur Aau", "name_hi": "सरनपुर आऊ" },
    { "name": "Saranpura", "name_hi": "सरनपुरा" },
    { "name": "Sarnada", "name_hi": "सरनाड़ा" },
    { "name": "Satasar", "name_hi": "सातासर" },
    { "name": "Sawal Nagar", "name_hi": "सावळ नगर" },
    { "name": "Sawalnagar Lohawat", "name_hi": "सांवळनगर लोहावट" },
    { "name": "Shaheed Gopal Nagar", "name_hi": "शहीद गोपाल नगर" },
    { "name": "Shaitan Singh Nagar", "name_hi": "शैतान सिंह नगर" },
    { "name": "Shakti Nagar", "name_hi": "शक्ति नगर" },
    { "name": "Sheirani Nagar", "name_hi": "शेरानी नगर" },
    { "name": "Shekhasar", "name_hi": "शेखासर" },
    { "name": "Shera Ram Nagar", "name_hi": "शेरा राम नगर" },
    { "name": "Sherpura", "name_hi": "शेरपुरा" },
    { "name": "Shimala", "name_hi": "शिमाला" },
    { "name": "Shiv Nagar", "name_hi": "शिव नगर" },
    { "name": "Shiv Sagar", "name_hi": "शिव सागर" },
    { "name": "Shivnagar", "name_hi": "शिवनगर" },
    { "name": "Shivnath Nagar", "name_hi": "शिवनाथ नगर" },
    { "name": "Shivpura", "name_hi": "शिवपुरा" },
    { "name": "Shivpuri", "name_hi": "शिवपुरी" },
    { "name": "Shree Surpura", "name_hi": "श्री सूरपुरा" },
    { "name": "Shri Jammeshwar Nagar", "name_hi": "श्री जामेश्वर नगर" },
    { "name": "Shyam Nagar", "name_hi": "श्याम नगर" },
    { "name": "Sihar Roopawaton Ki Dhani", "name_hi": "सिहर रूपावतों की ढाणी" },
    { "name": "Sihra", "name_hi": "सिहरा" },
    { "name": "Simra Thal", "name_hi": "सिमरा थल" },
    { "name": "Sindhi Pura", "name_hi": "सिन्धीपुरा" },
    { "name": "Singdasar", "name_hi": "सिंगदासर" },
    { "name": "Singhipura", "name_hi": "सिंघीपुरा" },
    { "name": "Siwandi", "name_hi": "सिवांडी" },
    { "name": "Siwandi Nadi", "name_hi": "सिवांडी नाड़ी" },
    { "name": "Siyagnagar", "name_hi": "सियाग नगर" },
    { "name": "Siyamali", "name_hi": "सियामली" },
    { "name": "Siyolnagar", "name_hi": "सियोल नगर" },
    { "name": "Soda Dhara", "name_hi": "सोड़ा धारा" },
    { "name": "Sodho Ka Mandal", "name_hi": "सोढों का मंडल" },
    { "name": "Sonalpura", "name_hi": "सोनालपुरा" },
    { "name": "Sonanda", "name_hi": "सोनंदा" },
    { "name": "Sri Krishan Nagar", "name_hi": "श्री कृष्ण नगर" },
    { "name": "Sri Krishnanagar", "name_hi": "श्री कृष्णनगर" },
    { "name": "Sri Lachhamannagar", "name_hi": "श्री लक्ष्मणनगर" },
    { "name": "Sri Lumbaramnagar Lohawat", "name_hi": "श्री लुम्बारामनगर लोहावट" },
    { "name": "Sri Mahadeo Nagar", "name_hi": "श्री महादेव नगर" },
    { "name": "Sri Mandroop Nagar", "name_hi": "श्री मंदरूप नगर" },
    { "name": "Sri Pabusar", "name_hi": "श्री पाबूसर" },
    { "name": "Sri Ram Deo Nagar Aau", "name_hi": "श्री रामदेव नगर आऊ" },
    { "name": "Sri Ram Nagar", "name_hi": "श्री राम नगर" },
    { "name": "Sri Ramnagar", "name_hi": "श्री रामनगर" },
    { "name": "Sri Rampura", "name_hi": "श्री रामपुरा" },
    { "name": "Subhash Nagar", "name_hi": "सुभाष नगर" },
    { "name": "Sukh Sagar", "name_hi": "सुख सागर" },
    { "name": "Sultan Nagar", "name_hi": "सुल्तान नगर" },
    { "name": "Sumrani Mangaliyon Ki Basti", "name_hi": "सुमरानी मंगालियों की बस्ती" },
    { "name": "Sunda Nagar", "name_hi": "सुंडा नगर" },
    { "name": "Sutharanada", "name_hi": "सूथरा नाड़ा" },
    { "name": "Suwap", "name_hi": "सुवाप" },
    { "name": "Swami Ji Ki Dhani", "name_hi": "स्वामी जी की ढाणी" },
    { "name": "Tanot Basti", "name_hi": "तानोट बस्ती" },
    { "name": "Tej Nagar", "name_hi": "तेज नगर" },
    { "name": "Tejasar", "name_hi": "तेजासर" },
    { "name": "Tekra", "name_hi": "टेकड़ा" },
    { "name": "Tenna Nadi", "name_hi": "तेन्ना नाड़ी" },
    { "name": "Thakriya Nada", "name_hi": "ठाकड़िया नाड़ा" },
    { "name": "Thata Nagar", "name_hi": "ठाटा नगर" },
    { "name": "Thoriyasar", "name_hi": "थोरियासर" },
    { "name": "Thoriyo Ka Bera", "name_hi": "ठोरियों का बेरा" },
    { "name": "Tikaram Paliwal Nagar", "name_hi": "टिकराम पालीवाल नगर" },
    { "name": "Tulsi Ram Nagar", "name_hi": "तुलसी राम नगर" },
    { "name": "Udainagar", "name_hi": "उदैनगर" },
    { "name": "Udaniyon Ki Dhani", "name_hi": "उदानीयों की ढाणी" },
    { "name": "Udat", "name_hi": "उडत" },
    { "name": "Udhav Nagar", "name_hi": "उद्धव नगर" },
    { "name": "Ugras", "name_hi": "उग्रास" },
    { "name": "Umani Nagar", "name_hi": "उमणी नगर" },
    { "name": "Ummed Nagar", "name_hi": "उम्मेद नगर" },
    { "name": "Vijai Nagar", "name_hi": "विजय नगर" },
    { "name": "Viram Nagar", "name_hi": "वीरम नगर" },
    { "name": "Visansar", "name_hi": "विसनसर" },
    { "name": "Vishnoi Chak", "name_hi": "विश्नोई चक" },
    { "name": "Vishnu Nagar", "name_hi": "विष्णु नगर" },
    { "name": "Vishnu Pura", "name_hi": "विष्णु पुरा" },
    { "name": "Vishnupura", "name_hi": "विष्णुपुरा" },
    { "name": "Vishvkarma Nagar", "name_hi": "विश्वकर्मा नगर" },
    { "name": "Vishwakarma Nagar", "name_hi": "विश्वकर्मा नगर" },
    { "name": "Vishwakarma Nagar Denok", "name_hi": "विश्वकर्मा नगर देनोक" }
  ]
}
,
   {
  "tehsil": "Shergarh",
  "villages": [
    { "name": "Aasoonagar", "name_hi": "आसू नगर" },
    { "name": "Abhaygarh", "name_hi": "अभयगढ़" },
    { "name": "Agolai", "name_hi": "आगोलाई" },
    { "name": "Ajeet Nagar", "name_hi": "अजीत नगर" },
    { "name": "Ajeetgarh", "name_hi": "अजीतगढ़" },
    { "name": "Alidas Nagar", "name_hi": "अलीदास नगर" },
    { "name": "Amar Nagar", "name_hi": "अमर नगर" },
    { "name": "Amar Pura", "name_hi": "अमरपुरा" },
    { "name": "Amrasar", "name_hi": "अमरसार" },
    { "name": "Amrit Nagar", "name_hi": "अमृत नगर" },
    { "name": "Anad Nagar", "name_hi": "आनंद नगर" },
    { "name": "Anandpura", "name_hi": "आनंदपुरा" },
    { "name": "Anandsar", "name_hi": "आनंदसर" },
    { "name": "Anopgarh", "name_hi": "अनूपगढ़" },
    { "name": "Anopnagar", "name_hi": "अनूपनगर" },
    { "name": "Anopsingh Nagar", "name_hi": "अनूपसिंह नगर" },
    { "name": "Asarlai", "name_hi": "आसरलाई" },
    { "name": "Baba Ramdeonagar", "name_hi": "बाबा रामदेवनगर" },
    { "name": "Babu Nagar", "name_hi": "बाबू नगर" },
    { "name": "Babu Singh Nagar", "name_hi": "बाबू सिंह नगर" },
    { "name": "Badargarh", "name_hi": "बादरगढ़" },
    { "name": "Badarsar", "name_hi": "बादरसर" },
    { "name": "Baghsagar", "name_hi": "बाघसागर" },
    { "name": "Bagiram Nagar", "name_hi": "बगीराम नगर" },
    { "name": "Bagtan Nagar", "name_hi": "बागतान नगर" },
    { "name": "Bahadur Nagar", "name_hi": "बहादुर नगर" },
    { "name": "Bahadurgarh", "name_hi": "बहादुरगढ़" },
    { "name": "Bakasar", "name_hi": "बाकासर" },
    { "name": "Balaji Nagar", "name_hi": "बालाजी नगर" },
    { "name": "Balanagar", "name_hi": "बाला नगर" },
    { "name": "Balasar", "name_hi": "बालासर" },
    { "name": "Baldev Nagar", "name_hi": "बलदेव नगर" },
    { "name": "Balesar Durgawatan", "name_hi": "बालेसर दुर्गावतन" },
    { "name": "Balesar Satan", "name_hi": "बालेसर सतन" },
    { "name": "Banesingh Nagar", "name_hi": "बनेसिंह नगर" },
    { "name": "Banon Ka Bas", "name_hi": "बन्यों का बास" },
    { "name": "Baori", "name_hi": "बावड़ी" },
    { "name": "Bapunagar", "name_hi": "बापू नगर" },
    { "name": "Barnau", "name_hi": "बरनाऊ" },
    { "name": "Basni Manna", "name_hi": "बसनी माणा" },
    { "name": "Bastawa", "name_hi": "बस्तावा" },
    { "name": "Bastawa Mataji", "name_hi": "बस्तावा माताजी" },
    { "name": "Bawarli", "name_hi": "बावरली" },
    { "name": "Beega Dev Nagar", "name_hi": "बीगा देव नगर" },
    { "name": "Belwa", "name_hi": "बेलवा" },
    { "name": "Belwa Ranaji", "name_hi": "बेलवा रानाजी" },
    { "name": "Berdo Ka Bas", "name_hi": "बेरड़ो का बास" },
    { "name": "Bhadasar", "name_hi": "भादासर" },
    { "name": "Bhagatgarh", "name_hi": "भगतगढ़" },
    { "name": "Bhagwan Nagar", "name_hi": "भगवान नगर" },
    { "name": "Bhairusingh Nagar", "name_hi": "भैरूसिंह नगर" },
    { "name": "Bhaloo Anopgarh", "name_hi": "भालू अनूपगढ़" },
    { "name": "Bhaloo Jawaharpura", "name_hi": "भालू जवाहरपुरा" },
    { "name": "Bhaloo Jogsar", "name_hi": "भालू जोगसर" },
    { "name": "Bhaloo Kalan", "name_hi": "भालू कलां" },
    { "name": "Bhaloo Kumbaniya", "name_hi": "भालू कुंबाणिया" },
    { "name": "Bhaloo Laxman Garh", "name_hi": "भालू लक्ष्मणगढ़" },
    { "name": "Bhaloo Rajwa", "name_hi": "भालू राजवा" },
    { "name": "Bhaloo Ratangarh", "name_hi": "भालू रतनगढ़" },
    { "name": "Bhaloo Udainagar", "name_hi": "भालू उदैनगर" },
    { "name": "Bhalu Deonagar", "name_hi": "भालू देवनगर" },
    { "name": "Bhalu Dungargarh", "name_hi": "भालू डूंगरगढ़" },
    { "name": "Bhalu Mahadeo Nagar", "name_hi": "भालू महादेव नगर" },
    { "name": "Bhalusher Nagar", "name_hi": "भालूशेर नगर" },
    { "name": "Bhandoo Charnan", "name_hi": "भांडू चारणन" },
    { "name": "Bhandoo Jati", "name_hi": "भांडू जाटी" },
    { "name": "Bhangarh", "name_hi": "भानगढ़" },
    { "name": "Bhatelai Charnan", "name_hi": "भटेलाई चारणन" },
    { "name": "Bhatelai Purohitan", "name_hi": "भटेलाई पुरोहितान" },
    { "name": "Bhatner Nagar", "name_hi": "भटनेर नगर" },
    { "name": "Bheekh Nagar", "name_hi": "भीख नगर" },
    { "name": "Bheewsagar", "name_hi": "भीवसागर" },
    { "name": "Bhernagar", "name_hi": "भेरनगर" },
    { "name": "Bheroo Nagar", "name_hi": "भेरू नगर" },
    { "name": "Bhom Sagar", "name_hi": "भोम सागर" },
    { "name": "Bhomasar", "name_hi": "भोमासर" },
    { "name": "Bhon Sagar", "name_hi": "भों सागर" },
    { "name": "Bhonasar", "name_hi": "भोनासर" },
    { "name": "Bhoongra", "name_hi": "भूंगरा" },
    { "name": "Bhoorsingh Nagar", "name_hi": "भूरसिंह नगर" },
    { "name": "Bhopal Nagar", "name_hi": "भोपाल नगर" },
    { "name": "Birad Nagar", "name_hi": "बिराड़ नगर" },
    { "name": "Birai", "name_hi": "बिराई" },
    { "name": "Biramdeogarh", "name_hi": "बीरमदेवगढ़" },
    { "name": "Biramsingh Nagar", "name_hi": "बीरा सिंह नगर" },
    { "name": "Budhsingh Nagar", "name_hi": "बूधसिंह नगर" },
    { "name": "Burkiya", "name_hi": "बुर्किया" },
    { "name": "Chaba", "name_hi": "छाबा" },
    { "name": "Chadoyat Nagar", "name_hi": "छदौयत नगर" },
    { "name": "Chain Singh Nagar", "name_hi": "चैनसिंह नगर" },
    { "name": "Chainsingh Nagar", "name_hi": "चैनसिंह नगर" },
    { "name": "Chakder", "name_hi": "चाकदर" },
    { "name": "Chamu", "name_hi": "चामू" },
    { "name": "Chanchalwa", "name_hi": "चांचलवा" },
    { "name": "Chand Sama", "name_hi": "चांद सामा" },
    { "name": "Chandsar", "name_hi": "चांदसर" },
    { "name": "Chauthgarh", "name_hi": "चौथगढ़" },
    { "name": "Chauthpura", "name_hi": "चौथपुरा" },
    { "name": "Chavnd Sagar", "name_hi": "छावंड सागर" },
    { "name": "Chhatargarh Hapa", "name_hi": "छतरगढ़ हापा" },
    { "name": "Chhatarsingh Nagar", "name_hi": "छतरसिंह नगर" },
    { "name": "Chimangarh", "name_hi": "चिमनगढ़" },
    { "name": "Chirwai", "name_hi": "चिरवाई" },
    { "name": "Chordiya", "name_hi": "छोरड़िया" },
    { "name": "Chutarpura", "name_hi": "चूतरपुरा" },
    { "name": "Dabla Nagar", "name_hi": "डाबला नगर" },
    { "name": "Dade Ki Beri", "name_hi": "डाडे की बेरी" },
    { "name": "Dalpatnagar", "name_hi": "दलपत नगर" },
    { "name": "Dansingh Nagar", "name_hi": "दानसिंह नगर" },
    { "name": "Dasaniyan", "name_hi": "दसानियां" },
    { "name": "Daulatgoga Nagar", "name_hi": "दौलतगोग़ा नगर" },
    { "name": "Daulatsingh Nagar", "name_hi": "दौलतसिंह नगर" },
    { "name": "Dechoo", "name_hi": "डेचू" },
    { "name": "Dedha Chak I", "name_hi": "देढा चक I" },
    { "name": "Dedha Chak Ii", "name_hi": "देढा चक II" },
    { "name": "Dedha Chak Iii", "name_hi": "देढा चक III" },
    { "name": "Deogarh", "name_hi": "देवगढ़" },
    { "name": "Deonagar", "name_hi": "देवनगर" },
    { "name": "Deorajgarh", "name_hi": "देवराजगढ़" },
    { "name": "Dera", "name_hi": "डेहरा" },
    { "name": "Deriya", "name_hi": "डेरिया" },
    { "name": "Devi Nagar", "name_hi": "देवी नगर" },
    { "name": "Devigarh", "name_hi": "देवगढ़" },
    { "name": "Dewaniya", "name_hi": "देवानिया" },
    { "name": "Dewatoo", "name_hi": "देवातू" },
    { "name": "Dhadhaniya Barda", "name_hi": "धाधानिया बाड़ा" },
    { "name": "Dhadhaniya Bhayla", "name_hi": "धाधानिया भायला" },
    { "name": "Dhadhaniya Sasan", "name_hi": "धाधानिया सासन" },
    { "name": "Dhan Sagar", "name_hi": "धान सागर" },
    { "name": "Dheerpura", "name_hi": "धीरपुरा" },
    { "name": "Dhokalsar", "name_hi": "धोकलसर" },
    { "name": "Dholasar", "name_hi": "धोलासर" },
    { "name": "Dhoom Sagar", "name_hi": "धूम सागर" },
    { "name": "Doodabera", "name_hi": "डूडाबेरा" },
    { "name": "Doodinagar", "name_hi": "डूडी नगर" },
    { "name": "Dugar", "name_hi": "दूगर" },
    { "name": "Dugarpura", "name_hi": "दूगरपुरा" },
    { "name": "Dungarpur", "name_hi": "डूंगरपुर" },
    { "name": "Durg Singh Pura", "name_hi": "दुर्गसिंह पुरा" },
    { "name": "Fateh Nagar", "name_hi": "फतेह नगर" },
    { "name": "Fatehgarh", "name_hi": "फतेहगढ़" },
    { "name": "Gaje Singh Nagar", "name_hi": "गजे सिंह नगर" },
    { "name": "Gajesinghnagar", "name_hi": "गजेसिंह नगर" },
    { "name": "Gajnawas", "name_hi": "गजनावास" },
    { "name": "Gajsinghpura", "name_hi": "गजसिंहपुरा" },
    { "name": "Ganganagar", "name_hi": "गंगानगर" },
    { "name": "Gangasar", "name_hi": "गंगासर" },
    { "name": "Gara", "name_hi": "गारा" },
    { "name": "Genan Garh", "name_hi": "गेनानगढ़" },
    { "name": "Ghudiyala", "name_hi": "घुडियाला" },
    { "name": "Gilakor", "name_hi": "गिलाकोर" },
    { "name": "Godasar", "name_hi": "गोदासर" },
    { "name": "Godelai", "name_hi": "गोड़ेलाई" },
    { "name": "Gogadeo Garh", "name_hi": "गोगादेवगढ़" },
    { "name": "Gokalsar Dev", "name_hi": "गोकलसर देव" },
    { "name": "Gokul Nagar", "name_hi": "गोकुल नगर" },
    { "name": "Gokulsingh Nagar", "name_hi": "गोकुलसिंह नगर" },
    { "name": "Gopal Pura", "name_hi": "गोपालपुरा" },
    { "name": "Gopalsar", "name_hi": "गोपालसर" },
    { "name": "Gosai Nagar", "name_hi": "गोसाई नगर" },
    { "name": "Govindpura", "name_hi": "गोविन्दपुरा" },
    { "name": "Gudiyasar", "name_hi": "गुडीयासर" },
    { "name": "Guman Nagar", "name_hi": "गुमान नगर" },
    { "name": "Guman Singh Nagar", "name_hi": "गुमानसिंह नगर" },
    { "name": "Gumanpura", "name_hi": "गुमानपुरा" },
    { "name": "Gumansinghpura", "name_hi": "गुमानसिंहपुरा" },
    { "name": "Hadman Garh", "name_hi": "हड़मानगढ़" },
    { "name": "Hanawant Nagar", "name_hi": "एनाउंत नगर" },
    { "name": "Hanif Sagar", "name_hi": "हनीफ सागर" },
    { "name": "Hanuman Nagar", "name_hi": "हनुमान नगर" },
    { "name": "Hanuman Sagar", "name_hi": "हनुमान सागर" },
    { "name": "Hanumanpura", "name_hi": "हनुमानपुरा" },
    { "name": "Hanwant Nagar", "name_hi": "हनवंत नगर" },
    { "name": "Hapasar", "name_hi": "हापासर" },
    { "name": "Haresingh Nagar", "name_hi": "हरेसिंह नगर" },
    { "name": "Hari Nagar", "name_hi": "हरि नगर" },
    { "name": "Hari Om Nagar", "name_hi": "हरिओम नगर" },
    { "name": "Hari Sagar", "name_hi": "हरि सागर" },
    { "name": "Hariom Nagar", "name_hi": "हरिओम नगर" },
    { "name": "Harisingh Nagar", "name_hi": "हरीसिंह नगर" },
    { "name": "Hariyana", "name_hi": "हरियाणा" },
    { "name": "Harmatnagar", "name_hi": "हरमत नगर" },
    { "name": "Harwantnagar", "name_hi": "हरवंत नगर" },
    { "name": "Hastinapur", "name_hi": "हस्तिनापुर" },
    { "name": "Hem Nagar", "name_hi": "हेम नगर" },
    { "name": "Hemawas", "name_hi": "हेमावास" },
    { "name": "Hemayant Nagar", "name_hi": "हेमायंत नगर" },
    { "name": "Hemsagar", "name_hi": "हेमसागर" },
    { "name": "Himmat Nagar", "name_hi": "हिम्मत नगर" },
    { "name": "Himmatpura", "name_hi": "हिम्मतपुरा" },
    { "name": "Hin Kuri", "name_hi": "हिन कुरी" },
    { "name": "Hinglaj Nagar", "name_hi": "हिंगलाज नगर" },
    { "name": "Hukam Singh Nagar", "name_hi": "हुकमसिंह नगर" },
    { "name": "Islamnagar", "name_hi": "इस्लामनगर" },
    { "name": "Islampura", "name_hi": "इस्लामपुरा" },
    { "name": "Jaisingh Pura", "name_hi": "जैसिंह पुरा" },
    { "name": "Jaitsar", "name_hi": "जैतसर" },
    { "name": "Jakharsar", "name_hi": "जाखरसर" },
    { "name": "Jalam Nagar", "name_hi": "जलम नगर" },
    { "name": "Jalandhar Nagar", "name_hi": "जालंधर नगर" },
    { "name": "Jalpuri", "name_hi": "जलपुरी" },
    { "name": "Jambheshwar Nagar", "name_hi": "जांभेश्वर नगर" },
    { "name": "Jambheswar Nagar", "name_hi": "जांभेश्वर नगर" },
    { "name": "Jamda Laxmangarh", "name_hi": "जामड़ा लक्ष्मणगढ़" },
    { "name": "Jamda Nagar", "name_hi": "जामड़ा नगर" },
    { "name": "Jatawas", "name_hi": "जटावास" },
    { "name": "Jawahar Nagar", "name_hi": "जवाहर नगर" },
    { "name": "Jawaharpura", "name_hi": "जवाहरपुरा" },
    { "name": "Jeejniyala Govinda", "name_hi": "जीजनीयाला गोविन्द" },
    { "name": "Jeevraj Nagar", "name_hi": "जीवराज नगर" },
    { "name": "Jeeyaberi", "name_hi": "जीयाबेरी" },
    { "name": "Jethaniya", "name_hi": "जेठानिया" },
    { "name": "Jethu Singh Nagar", "name_hi": "जेठूसिंह नगर" },
    { "name": "Jetsar", "name_hi": "जेटसर" },
    { "name": "Jhinjhaniyala", "name_hi": "झिंझनियाला" },
    { "name": "Jhubar Ka Ray", "name_hi": "झुबर का रेय" },
    { "name": "Jiyabera", "name_hi": "जियाबेरा" },
    { "name": "Jogidas Nagar", "name_hi": "जोगीदास नगर" },
    { "name": "Jognagar", "name_hi": "जोगनगर" },
    { "name": "Jograj Nagar", "name_hi": "जोगराज नगर" },
    { "name": "Judiya", "name_hi": "जुडिया" },
    { "name": "Junader", "name_hi": "जूनादेर" },
    { "name": "Kachhab Nagar", "name_hi": "कच्छब नगर" },
    { "name": "Kalani Nagar", "name_hi": "कलानी नगर" },
    { "name": "Kalau", "name_hi": "कलाऊ" },
    { "name": "Kalu Singh Nagar", "name_hi": "कालूसिंह नगर" },
    { "name": "Kalyan Singh Nagar", "name_hi": "कल्याणसिंह नगर" },
    { "name": "Kanasar", "name_hi": "कनासर" },
    { "name": "Kanodiya Mahasingh", "name_hi": "कनोडिया महा सिंह" },
    { "name": "Kanodiya Purohitan", "name_hi": "कनोडिया पुरोहितान" },
    { "name": "Kansingh Nagar", "name_hi": "कनसिंह नगर" },
    { "name": "Karansinghnagar", "name_hi": "करनसिंह नगर" },
    { "name": "Karlai Nagar", "name_hi": "करलाई नगर" },
    { "name": "Karni Nagar", "name_hi": "करणी नगर" },
    { "name": "Karnisar", "name_hi": "करनीसर" },
    { "name": "Kasu Ram Nagar", "name_hi": "कासूराम नगर" },
    { "name": "Kerala", "name_hi": "केरला" },
    { "name": "Kerla Nagar", "name_hi": "केरला नगर" },
    { "name": "Kesar Garh", "name_hi": "केसरगढ़" },
    { "name": "Kesariya Kanwar Nagar", "name_hi": "केसरिया कंवर नगर" },
    { "name": "Ketoo Hema", "name_hi": "केटू हेम" },
    { "name": "Ketoo Kalan", "name_hi": "केटू कलां" },
    { "name": "Ketoo Manawata", "name_hi": "केटू मनावट" },
    { "name": "Ketoo Manda", "name_hi": "केटू मण्डा" },
    { "name": "Khadingsar", "name_hi": "खादिंगसर" },
    { "name": "Khanori", "name_hi": "खनोरी" },
    { "name": "Khari Beri", "name_hi": "खारी बेरी" },
    { "name": "Khemasar", "name_hi": "खेमासर" },
    { "name": "Kherajgarh", "name_hi": "खेराजगढ़" },
    { "name": "Khet Nagar", "name_hi": "खेड़ नगर" },
    { "name": "Khetasar", "name_hi": "खेता‍सर" },
    { "name": "Kheteswar Nagar", "name_hi": "खेतेश्वर नगर" },
    { "name": "Khetsagar", "name_hi": "खेतसागर" },
    { "name": "Khetsingh Nagar", "name_hi": "खेतसिंह नगर" },
    { "name": "Khirjan Asha", "name_hi": "खिरजान आशा" },
    { "name": "Khirjan Bhoja", "name_hi": "खिरजान भोजा" },
    { "name": "Khirjan Fatehsingh", "name_hi": "खिरजान फतेहसिंह" },
    { "name": "Khirjan Khas", "name_hi": "खिरजान खास" },
    { "name": "Khirjan Tibna", "name_hi": "खिरजान तिबना" },
    { "name": "Khiyasariya", "name_hi": "खियासरिया" },
    { "name": "Khudiyala", "name_hi": "खुडियाला" },
    { "name": "Khumsar", "name_hi": "खूमसर" },
    { "name": "Kishanpura", "name_hi": "किशनपुरा" },
    { "name": "Kishor Nagar", "name_hi": "किशोर नगर" },
    { "name": "Konari", "name_hi": "कोनाड़ी" },
    { "name": "Kui Inda", "name_hi": "कूई इंदा" },
    { "name": "Kui Jodha", "name_hi": "कूई जोधा" },
    { "name": "Lakhasar", "name_hi": "लखासर" },
    { "name": "Lal Nagar", "name_hi": "लाल नगर" },
    { "name": "Lal Sagar", "name_hi": "लाल सागर" },
    { "name": "Lalpura", "name_hi": "लालपुरा" },
    { "name": "Lalsar", "name_hi": "लालसर" },
    { "name": "Lalsingh Nagar", "name_hi": "लालसिंह नगर" },
    { "name": "Lawaran", "name_hi": "लावरन" },
    { "name": "Laxman Nagar", "name_hi": "लक्ष्मण नगर" },
    { "name": "Laxmangarh", "name_hi": "लक्ष्मणगढ़" },
    { "name": "Lichman Nagar", "name_hi": "लिचमन नगर" },
    { "name": "Lodta Achlawata", "name_hi": "लोडता अचलावाता" },
    { "name": "Lodta Haridasot", "name_hi": "लोडता हरिदासोत" },
    { "name": "Lubhansar", "name_hi": "लुभांसर" },
    { "name": "Lumbansar", "name_hi": "लुम्बनसर" },
    { "name": "Lunaopura", "name_hi": "लूणाऊपुरा" },
    { "name": "Ma Sati Nagar", "name_hi": "मा सती नगर" },
    { "name": "Madasar", "name_hi": "मदासर" },
    { "name": "Madroop Nagar", "name_hi": "मद्रूप नगर" },
    { "name": "Magasar", "name_hi": "मगासर" },
    { "name": "Mahadeo Nagar", "name_hi": "महादेव नगर" },
    { "name": "Mahesh Das Nagar", "name_hi": "महेशदास नगर" },
    { "name": "Malinath Nagar", "name_hi": "मालीनाथ नगर" },
    { "name": "Man Singh Nagar", "name_hi": "मानसिंह नगर" },
    { "name": "Mangalsingh Nagar", "name_hi": "मंगलसिंह नगर" },
    { "name": "Manoharsingh Nagar", "name_hi": "मनहरसिंह नगर" },
    { "name": "Meerpura", "name_hi": "मीरपुरा" },
    { "name": "Meghasar", "name_hi": "मेघासर" },
    { "name": "Mehoji Nagar", "name_hi": "मेहोजी नगर" },
    { "name": "Mehtab Garh", "name_hi": "मेहताबगढ़" },
    { "name": "Mejal Nagar", "name_hi": "मेजल नगर" },
    { "name": "Merajsingh Nagar", "name_hi": "मेराजसिंह नगर" },
    { "name": "Meriya", "name_hi": "मेरिया" },
    { "name": "Modsingh Nagar", "name_hi": "मोदसिंह नगर" },
    { "name": "Mohkamgarh", "name_hi": "मोखमगढ़" },
    { "name": "Momatgarh", "name_hi": "मोमतगढ़" },
    { "name": "Mooleji Ka Bera", "name_hi": "मूलेजी का बेरा" },
    { "name": "Moondsar", "name_hi": "मूंडसर" },
    { "name": "Morya Nagar", "name_hi": "मोऱ्या नगर" },
    { "name": "Motalji Ka Bas", "name_hi": "मोतलजी का बास" },
    { "name": "Moti Nagar", "name_hi": "मोती नगर" },
    { "name": "Moti Sagar", "name_hi": "मोती सागर" },
    { "name": "Moti Singh Nagar", "name_hi": "मोतिसिंह नगर" },
    { "name": "Motisar", "name_hi": "मोटीसर" },
    { "name": "Motisingh Nagar", "name_hi": "मोतिसिंह नगर" },
    { "name": "Mukansar", "name_hi": "मुखनसर" },
    { "name": "Muknasar", "name_hi": "मुखनासर" },
    { "name": "Nagsinghpura", "name_hi": "नागसिंहपुरा" },
    { "name": "Naharsingh Nagar", "name_hi": "नाहरसिंह नगर" },
    { "name": "Narayan Nagar", "name_hi": "नारायण नगर" },
    { "name": "Narsinghpura", "name_hi": "नरसिंहपुरा" },
    { "name": "Nathasar", "name_hi": "नाथासर" },
    { "name": "Nathrau", "name_hi": "नाथराउ" },
    { "name": "Nathusingh Nagar", "name_hi": "नाथूसिंह नगर" },
    { "name": "Navalgarh", "name_hi": "नवलगढ़" },
    { "name": "Nawalsar", "name_hi": "नवलसर" },
    { "name": "Navabera", "name_hi": "नवाबेरा" },
    { "name": "Nayasara", "name_hi": "नयसरा" },
    { "name": "Nimbon Ka Gaon", "name_hi": "निंबों का गांव" },
    { "name": "Paboo Chhawara", "name_hi": "पाबू छवाड़ा" },
    { "name": "Pabu Nagar", "name_hi": "पाबू नगर" },
    { "name": "Paboogarh", "name_hi": "पाबूगढ़" },
    { "name": "Paboosar", "name_hi": "पाबूसर" },
    { "name": "Padamgarh", "name_hi": "पदमगढ़" },
    { "name": "Padampur", "name_hi": "पदमपुर" },
    { "name": "Paliwal Nagar", "name_hi": "पालीवाल नगर" },
    { "name": "Panditon Ka Bas", "name_hi": "पंडितों का बास" },
    { "name": "Pannasar", "name_hi": "पन्नासर" },
    { "name": "Panne Singh Nagar", "name_hi": "पन्नेसिंह नगर" },
    { "name": "Pannisar", "name_hi": "पन्नीसर" },
    { "name": "Prahladpura", "name_hi": "प्रहलादपुरा" },
    { "name": "Pratap Sagar", "name_hi": "प्रताप सागर" },
    { "name": "Pratapgarh", "name_hi": "प्रतापगढ़" },
    { "name": "Premnagar", "name_hi": "प्रेम नगर" },
    { "name": "Premsagar", "name_hi": "प्रेम सागर" },
    { "name": "Premsar", "name_hi": "प्रेमसर" },
    { "name": "Premsingh Nagar", "name_hi": "प्रेमसिंह नगर" },
    { "name": "Prithviraj Nagar", "name_hi": "पृथ्वीराज नगर" },
    { "name": "Pugaliya", "name_hi": "पुगालिया" },
    { "name": "Punasar", "name_hi": "पूनासर" },
    { "name": "Punawat Nagar", "name_hi": "पुनावत नगर" },
    { "name": "Punjraj Nagar", "name_hi": "पुंजराज नगर" },
    { "name": "Raghunath Pura", "name_hi": "रघुनाथपुरा" },
    { "name": "Raghunath Singh Nagar", "name_hi": "रघुनाथसिंह नगर" },
    { "name": "Raidhanpura", "name_hi": "रैधानपुरा" },
    { "name": "Raisar", "name_hi": "राईसर" },
    { "name": "Rajabandh", "name_hi": "राजाबंध" },
    { "name": "Rajendra Nagar", "name_hi": "राजेन्द्र नगर" },
    { "name": "Rajgarh", "name_hi": "राजगढ़" },
    { "name": "Rajsagar", "name_hi": "राजसागर" },
    { "name": "Ram Nagar", "name_hi": "राम नगर" },
    { "name": "Ram Singh Pura", "name_hi": "रामसिंह पुरा" },
    { "name": "Ramchandrani Nagar", "name_hi": "रामचन्द्राणी नगर" },
    { "name": "Ramdeo Nagar", "name_hi": "रामदेव नगर" },
    { "name": "Ramdev Nagar", "name_hi": "रामदेव नगर" },
    { "name": "Ramdevnagar", "name_hi": "रामदेव नगर" },
    { "name": "Ramdhan Garh", "name_hi": "रामधनगढ़" },
    { "name": "Ramgarh", "name_hi": "रामगढ़" },
    { "name": "Ramnagar", "name_hi": "रामनगर" },
    { "name": "Ramsagar", "name_hi": "रामसागर" },
    { "name": "Ramsar", "name_hi": "रामसर" },
    { "name": "Ramsingh Nagar", "name_hi": "रामसिंह नगर" },
    { "name": "Ramu Nagar", "name_hi": "रामू नगर" },
    { "name": "Ranasar", "name_hi": "राणासर" },
    { "name": "Ranchodsingh Garh", "name_hi": "रंचोदसिंहगढ़" },
    { "name": "Ranjeet Garh", "name_hi": "रंजीतगढ़" },
    { "name": "Ranjeet Sagar", "name_hi": "रंजीत सागर" },
    { "name": "Ranjeet Singh Nagar", "name_hi": "रंजीतसिंह नगर" },
    { "name": "Ranjeetnagar", "name_hi": "रंजीतनगर" },
    { "name": "Ranjit Garh", "name_hi": "रंजीतगढ़" },
    { "name": "Rankeshwar Nagar", "name_hi": "रंकेश्वर नगर" },
    { "name": "Ratangarh", "name_hi": "रतनगढ़" },
    { "name": "Ratanpura", "name_hi": "रतनपुरा" },
    { "name": "Ratansar", "name_hi": "रतनसर" },
    { "name": "Ratneshwar Nagar", "name_hi": "रत्नेश्वर नगर" },
    { "name": "Rawalgarh", "name_hi": "रावलगढ़" },
    { "name": "Rawatgarh", "name_hi": "रावतगढ़" },
    { "name": "Rawatsar", "name_hi": "रावतसर" },
    { "name": "Rewatsingh Nagar", "name_hi": "रेवतकसिंह नगर" },
    { "name": "Roop Nagar", "name_hi": "रूप नगर" },
    { "name": "Roopnagar", "name_hi": "रूपनगर" },
    { "name": "Run Area", "name_hi": "रन एरिया" },
    { "name": "Sabalgarh", "name_hi": "सबलगढ़" },
    { "name": "Sabarsar", "name_hi": "सबासर" },
    { "name": "Sadulnagar", "name_hi": "सादुलनगर" },
    { "name": "Sadulpura", "name_hi": "सादुलपुरा" },
    { "name": "Sagat Nagar", "name_hi": "सगत नगर" },
    { "name": "Sagran", "name_hi": "सागरण" },
    { "name": "Saheed Jorsingh Nagar", "name_hi": "शहीद जोरसिंह नगर" },
    { "name": "Saheed Pehapnagar", "name_hi": "शहीद पहप नगर" },
    { "name": "Sai", "name_hi": "साई" },
    { "name": "Saidpura", "name_hi": "सइदपुरा" },
    { "name": "Sajjansagar", "name_hi": "सज्जनसागर" },
    { "name": "Salasar Nagar", "name_hi": "सलासर नगर" },
    { "name": "Sang Singh Nagar", "name_hi": "सांगसिंह नगर" },
    { "name": "Sang Singh Pura", "name_hi": "सांगसिंह पुरा" },
    { "name": "Santosh Nathpura", "name_hi": "सन्तोषनाथपुरा" },
    { "name": "Santoshnagar", "name_hi": "संतोषनगर" },
    { "name": "Sanwalon Ki Dhani", "name_hi": "सांवलों की ढाणी" },
    { "name": "Saran Nagar", "name_hi": "सरन नगर" },
    { "name": "Sati Mata Nagar", "name_hi": "सती माता नगर" },
    { "name": "Sayab Nagar", "name_hi": "सायब नगर" },
    { "name": "Setrawa", "name_hi": "सेतरावा" },
    { "name": "Shaheed Ganpat Singh Nagar", "name_hi": "शहीद गणपतसिंह नगर" },
    { "name": "Shaheed Megsingh Nagar", "name_hi": "शहीद मेघसिंह नगर" },
    { "name": "Shekhala", "name_hi": "शेखाला" },
    { "name": "Shergarh", "name_hi": "शेरगढ़" },
    { "name": "Shimbhugarh", "name_hi": "शिंभूगढ़" },
    { "name": "Shiv Nath Singh Nagar", "name_hi": "शिवनाथसिंह नगर" },
    { "name": "Shivpura", "name_hi": "शिवपुरा" },
    { "name": "Shivsagar", "name_hi": "शिवसागर" },
    { "name": "Shivsar", "name_hi": "शिवसर" },
    { "name": "Shri Anop Singh Nagar", "name_hi": "श्री अनोपसिंह नगर" },
    { "name": "Shri Khetsingh Nagar", "name_hi": "श्री खेतसिंह नगर" },
    { "name": "Shri Mohangarh", "name_hi": "श्री मोहनगढ़" },
    { "name": "Shri Ranusingh Nagar", "name_hi": "श्री रणूसिंह नगर" },
    { "name": "Simrathpura", "name_hi": "सिमरतपुरा" },
    { "name": "Sirada", "name_hi": "सिराड़ा" },
    { "name": "Siyanda", "name_hi": "सियांदा" },
    { "name": "Sohangarh", "name_hi": "सोहनगढ़" },
    { "name": "Sohansingh Nagar", "name_hi": "सोहनसिंह नगर" },
    { "name": "Sointara", "name_hi": "सोईंतरा" },
    { "name": "Solkiya Tala", "name_hi": "सोलकिया ताला" },
    { "name": "Somesar", "name_hi": "सोमेसर" },
    { "name": "Sri Karansingh Nagar", "name_hi": "श्री करनसिंह नगर" },
    { "name": "Sri Ram Nagar", "name_hi": "श्री राम नगर" },
    { "name": "Sujan Nagar", "name_hi": "सुब्जान नगर" },
    { "name": "Sukh Sagar", "name_hi": "सुख सागर" },
    { "name": "Sukhmandla", "name_hi": "सुखमण्डला" },
    { "name": "Sultansingh Nagar", "name_hi": "सुल्तानसिंह नगर" },
    { "name": "Surani", "name_hi": "सुरानी" },
    { "name": "Surya Nagar", "name_hi": "सूर्य नगर" },
    { "name": "Surya Udainagar", "name_hi": "सूर्य उदैनगर" },
    { "name": "Suwaliya", "name_hi": "सुवालिया" },
    { "name": "Suweri Sansan", "name_hi": "सुवेरी सासण" },
    { "name": "Teekamgarh", "name_hi": "टीकमगढ़" },
    { "name": "Tejsingh Nagar", "name_hi": "तेजसिंह नगर" },
    { "name": "Telasar", "name_hi": "टेलासर" },
    { "name": "Tena", "name_hi": "तेना" },
    { "name": "Thadiya", "name_hi": "ठाडिया" },
    { "name": "Tikamsingh Nagar", "name_hi": "टीकंसिंह नगर" },
    { "name": "Tilan Nagar", "name_hi": "तिलन नगर" },
    { "name": "Timbari", "name_hi": "टिंबरी" },
    { "name": "Tolesar Charnan", "name_hi": "टोलेसर चारणन" },
    { "name": "Tolesar Purohitan", "name_hi": "टोलेसर पुरोहितान" },
    { "name": "Udaisar", "name_hi": "उदईसर" },
    { "name": "Udasar", "name_hi": "उदासर" },
    { "name": "Ummed Nagar", "name_hi": "उम्मेद नगर" },
    { "name": "Ummedgarh", "name_hi": "उम्मेदगढ़" },
    { "name": "Uraj Nagar", "name_hi": "उराज नगर" },
    { "name": "Utambar", "name_hi": "उतम्बर" },
    { "name": "Uttamsingh Nagar", "name_hi": "उत्तमसिंह नगर" },
    { "name": "Utwaliya", "name_hi": "उटवालिया" },
    { "name": "Veeram Pura", "name_hi": "वीरमपुरा" },
    { "name": "Veeramgarh", "name_hi": "वीरमगढ़" },
    { "name": "Veerampura", "name_hi": "वीरमपुरा" },
    { "name": "Veeramsar", "name_hi": "वीरमसर" },
    { "name": "Soontara", "name_hi": "सूंंटरा" },
    { "name": "Vijay Singh Nagar", "name_hi": "विजयसिंह नगर" },
    { "name": "Viram Nagar", "name_hi": "वीरम नगर" },
    { "name": "Vishan Nagar", "name_hi": "विशन नगर" },
    { "name": "Vishnu Nagar", "name_hi": "विष्णु नगर" },
    { "name": "Vishvakarma Nagar", "name_hi": "विश्वकर्मा नगर" },
    { "name": "Vishvakrma Nagar", "name_hi": "विश्वकर्मा नगर" },
    { "name": "Vishwakarma Nagar", "name_hi": "विश्वकर्मा नगर" }
  ]
}
  ]}